{"\u0633\u0627\u0646\u0686\u06c1:Coord": [], "\u0633\u0627\u0646\u0686\u06c1:\u062d\u0648\u0627\u0644\u06c1 \u062c\u0627\u062a": [{"sw": "colwidth", "ur": "colwidth", "d": 0.3946476131873309}, {"sw": "refs", "ur": "refs", "d": 0.3988661762223207}], "\u0633\u0627\u0646\u0686\u06c1:Wayback": [{"sw": "date", "ur": "date", "d": 0.4466904447836726}], "\u0633\u0627\u0646\u0686\u06c1:Citation": [{"sw": "location", "ur": "location", "d": 0.2820954195842367}, {"sw": "accessdate", "ur": "access-date", "d": 0.3579150174837954}, {"sw": "archive-date", "ur": "archive-date", "d": 0.37336097426420745}, {"sw": "display-editors", "ur": "quote", "d": 0.3858580737592351}, {"sw": "access-date", "ur": "accessdate", "d": 0.400289944394144}, {"sw": "author-link", "ur": "archive-url", "d": 0.425449139432325}, {"sw": "date", "ur": "date", "d": 0.4466904447836726}], "\u0633\u0627\u0646\u0686\u06c1:Sfn": [], "\u0633\u0627\u0646\u0686\u06c1:Div col": [{"sw": "colwidth", "ur": "colwidth", "d": 0.3946476131873309}, {"sw": "cols", "ur": "cols", "d": 0.4045146250518217}], "\u0633\u0627\u0646\u0686\u06c1:Infobox settlement": [{"sw": "map_caption", "ur": "dot_map_caption", "d": 0.2665624770740024}, {"sw": "pushpin_map_caption", "ur": "pushpin_map_caption", "d": 0.28352343463865226}, {"sw": "image_map", "ur": "image_map", "d": 0.34325402959754825}, {"sw": "pushpin_map", "ur": "image_dot_map", "d": 0.3457070436576948}, {"sw": "population_as_of", "ur": "population_as_of", "d": 0.3533620422960815}, {"sw": "mapsize", "ur": "map_alt1", "d": 0.38083229819242315}, {"sw": "pushpin_mapsize", "ur": "dot_mapsize", "d": 0.3850109489663872}, {"sw": "blank_name", "ur": "named_for", "d": 0.3952237149087915}, {"sw": "established_date", "ur": "established_date3", "d": 0.40023742453045985}, {"sw": "utc_offset_dst", "ur": "utc_offset_dst", "d": 0.4017566297558398}, {"sw": "elevation_ft", "ur": "elevation_ft", "d": 0.4021623985261995}, {"sw": "population_note", "ur": "pushpin_map_alt", "d": 0.41651780937115657}, {"sw": "subdivision_type3", "ur": "subdivision_name2", "d": 0.4199640450150759}, {"sw": "population_year", "ur": "pop_est_as_of", "d": 0.42237815259252043}, {"sw": "subdivision_type1", "ur": "subdivision_name1", "d": 0.4251673798346419}, {"sw": "timezone_dst", "ur": "utc_offset1_dst", "d": 0.42587814187985973}, {"sw": "established_title", "ur": "established_title2", "d": 0.4266242643900928}, {"sw": "subdivision_name", "ur": "subdivision_name4", "d": 0.42803603416162095}, {"sw": "postal_code", "ur": "postal_code_type", "d": 0.43363232530354745}, {"sw": "coordinates_region", "ur": "area_blank1_title", "d": 0.4365108415915159}, {"sw": "subdivision_type2", "ur": "subdivision_name3", "d": 0.43791514142402344}, {"sw": "population_density_km2", "ur": "elevation_m_max", "d": 0.4414991455794379}, {"sw": "elevation_footnotes", "ur": "map_caption", "d": 0.4418858020371683}, {"sw": "coordinates_type", "ur": "blank3_info_sec1", "d": 0.444617581746069}, {"sw": "image_caption", "ur": "map_caption1", "d": 0.44790006893378564}, {"sw": "utc_offset", "ur": "utc_offset", "d": 0.4488310907276588}], "\u0633\u0627\u0646\u0686\u06c1:\u0645\u0631\u062f\u06c1 \u0631\u0628\u0637": [{"sw": "fix-attempted", "ur": "fix-attempted", "d": 0.34119746972276566}, {"sw": "date", "ur": "date", "d": 0.4466904447836726}], "\u0633\u0627\u0646\u0686\u06c1:Infobox country": [{"sw": "image_map", "ur": "image_map", "d": 0.34325402959754825}, {"sw": "sovereignty_note", "ur": "conventional_long_name", "d": 0.4203619053087654}], "\u0633\u0627\u0646\u0686\u06c1:Webarchive": [{"sw": "date", "ur": "date", "d": 0.4466904447836726}], "\u0633\u0627\u0646\u0686\u06c1:\u062a\u062d\u0648\u06cc\u0644": [{"sw": "abbr", "ur": "sigfig", "d": 0.39687486754416834}, {"sw": "adj", "ur": "sortable", "d": 0.44129743810796895}], "\u0633\u0627\u0646\u0686\u06c1:Location map": [{"sw": "float", "ur": "marksize", "d": 0.4019917282151192}, {"sw": "lon_deg", "ur": "lon_deg", "d": 0.44678218566594485}], "\u0633\u0627\u0646\u0686\u06c1:Cite report": [{"sw": "archivedate", "ur": "archivedate", "d": 0.3558245339621884}, {"sw": "accessdate", "ur": "access-date", "d": 0.3579150174837954}, {"sw": "archiveurl", "ur": "archiveurl", "d": 0.41297508350593526}, {"sw": "date", "ur": "date", "d": 0.4466904447836726}], "\u0633\u0627\u0646\u0686\u06c1:\u062d\u0648\u0627\u0644\u06c1 \u06a9\u062a\u0627\u0628": [{"sw": "location", "ur": "location", "d": 0.2820954195842367}, {"sw": "display-authors", "ur": "quote", "d": 0.3393714065445642}, {"sw": "accessdate", "ur": "access-date", "d": 0.3579150174837954}, {"sw": "archivedate", "ur": "archive-date", "d": 0.3672482839873912}, {"sw": "authorlink", "ur": "oclc", "d": 0.37441301941724947}, {"sw": "quote", "ur": "editor-last", "d": 0.39059406207778447}, {"sw": "coauthors", "ur": "editor-first", "d": 0.40507285395458104}, {"sw": "archive-date", "ur": "archive-url", "d": 0.41678933412872077}, {"sw": "deadurl", "ur": "url-access", "d": 0.43291826150726076}, {"sw": "date", "ur": "date", "d": 0.4466904447836726}, {"sw": "archiveurl", "ur": "url", "d": 0.4481146401022431}], "\u0633\u0627\u0646\u0686\u06c1:\u062d\u0648\u0627\u0644\u06c1 \u0648\u06cc\u0628": [{"sw": "quote", "ur": "deadurl", "d": 0.3442373515596028}, {"sw": "coauthors", "ur": "quote", "d": 0.35407497667225596}, {"sw": "archivedate", "ur": "archivedate", "d": 0.3558245339621884}, {"sw": "accessdate", "ur": "access-date", "d": 0.3579150174837954}, {"sw": "archive-date", "ur": "archive-date", "d": 0.37336097426420745}, {"sw": "access-date", "ur": "accessdate", "d": 0.400289944394144}, {"sw": "archiveurl", "ur": "archiveurl", "d": 0.41297508350593526}, {"sw": "authorlink", "ur": "archive-url", "d": 0.43422757361637554}, {"sw": "date", "ur": "date", "d": 0.4466904447836726}], "\u0633\u0627\u0646\u0686\u06c1:\u062e\u0627\u0646\u06c2 \u0645\u0639\u0644\u0648\u0645\u0627\u062a \u06a9\u062a\u0627\u0628": [{"sw": "country", "ur": "country", "d": 0.2974063084275377}, {"sw": "release_date", "ur": "pub_date", "d": 0.3710962017175222}, {"sw": "english_release_date", "ur": "oclc", "d": 0.4118772441528409}], "\u0633\u0627\u0646\u0686\u06c1:Start date and age": [{"sw": "df", "ur": "df", "d": 0.4146209580088852}], "\u0633\u0627\u0646\u0686\u06c1:\u0628\u0644\u0627 \u062d\u0648\u0627\u0644\u06c1": [{"sw": "date", "ur": "date", "d": 0.4466904447836726}], "\u0633\u0627\u0646\u0686\u06c1:\u062a\u0627\u0631\u06cc\u062e \u0648\u0641\u0627\u062a \u0627\u0648\u0631 \u0639\u0645\u0631": [{"sw": "df", "ur": "df", "d": 0.4146209580088852}], "\u0633\u0627\u0646\u0686\u06c1:\u062e\u0627\u0646\u06c1 \u0645\u0639\u0644\u0648\u0645\u0627\u062a \u0635\u0627\u062d\u0628 \u0645\u0646\u0635\u0628": [{"sw": "birth_date", "ur": "birth_date", "d": 0.4101536586066087}], "\u0633\u0627\u0646\u0686\u06c1:\u062e\u0627\u0646\u06c1 \u0645\u0639\u0644\u0648\u0645\u0627\u062a \u0641\u0644\u0645": [], "\u0633\u0627\u0646\u0686\u06c1:Dagger": [], "\u0633\u0627\u0646\u0686\u06c1:\u062d\u0648\u0627\u0644\u06c1 \u0631\u0633\u0627\u0644\u06c1": [{"sw": "pmid", "ur": "access-date", "d": 0.33733829712434127}, {"sw": "pmc", "ur": "doi", "d": 0.3699089661414606}, {"sw": "accessdate", "ur": "accessdate", "d": 0.38413791966032707}, {"sw": "display-authors", "ur": "pages", "d": 0.4134762677446022}, {"sw": "arxiv", "ur": "url", "d": 0.4141488678029094}, {"sw": "date", "ur": "date", "d": 0.4466904447836726}]}