{"Template:Taxobox": [{"bh": "name", "en": "name", "d": 0.21803344649687106}, {"bh": "image", "en": "image", "d": 0.22816033235718702}, {"bh": "image_caption", "en": "image_caption", "d": 0.28013859500029614}, {"bh": "image_width", "en": "image_width", "d": 0.2883721324880065}, {"bh": "image2", "en": "image caption", "d": 0.29168591421684253}, {"bh": "range_map_caption", "en": "range_map_caption", "d": 0.29669515200477414}, {"bh": "image2_caption", "en": "image2_caption", "d": 0.32785731595793943}, {"bh": "range_map_width", "en": "range_map", "d": 0.3698161126090831}, {"bh": "genus", "en": "type_species", "d": 0.3992885008439929}, {"bh": "species", "en": "species", "d": 0.417538146665391}, {"bh": "synonyms_ref", "en": "status_ref", "d": 0.42149812975188283}, {"bh": "range_map_alt", "en": "image_size", "d": 0.43823809209670306}, {"bh": "synonyms", "en": "synonyms_ref", "d": 0.44643632199761396}, {"bh": "subdivision", "en": "subdivisio", "d": 0.4485617483948108}, {"bh": "genus_authority", "en": "type_species_authority", "d": 0.4489615070434153}], "Template:Cite journal": [{"bh": "location", "en": "location", "d": 0.060850258779650335}, {"bh": "pages", "en": "pages", "d": 0.2532667706021383}, {"bh": "date", "en": "date", "d": 0.25855963384196023}, {"bh": "page", "en": "page", "d": 0.30010879197599183}, {"bh": "url", "en": "url", "d": 0.3011189705043299}, {"bh": "archivedate", "en": "archive-date", "d": 0.3250035585238501}, {"bh": "year", "en": "year", "d": 0.3251210168676537}, {"bh": "archiveurl", "en": "archive-url", "d": 0.33783504287025934}, {"bh": "arxiv", "en": "author-link", "d": 0.34840182485454574}, {"bh": "language", "en": "language", "d": 0.3662079943960146}, {"bh": "format", "en": "format", "d": 0.3769724366771072}, {"bh": "title", "en": "title", "d": 0.40172178962714566}, {"bh": "pmc", "en": "author-link2", "d": 0.4030525144787357}, {"bh": "vauthors", "en": "author-last", "d": 0.4108726363346099}, {"bh": "display-authors", "en": "display-authors", "d": 0.42983641402679706}, {"bh": "bibcode", "en": "bibcode", "d": 0.44095604041705694}, {"bh": "pmid", "en": "author2-link", "d": 0.4412594176433482}, {"bh": "s2cid", "en": "id", "d": 0.44544029981364264}], "Template:Taxonbar": [{"bh": "from1", "en": "from", "d": 0.41503897907180354}], "Template:Infobox military unit": [{"bh": "image", "en": "image", "d": 0.22816033235718702}, {"bh": "image_size", "en": "image_size", "d": 0.2591931448675111}, {"bh": "country", "en": "country", "d": 0.31025609414271993}, {"bh": "start_date", "en": "start_date", "d": 0.34655123607344285}, {"bh": "identification_symbol_label", "en": "identification_symbol_label", "d": 0.38929320922893673}, {"bh": "garrison_label", "en": "identification_symbol_4_label", "d": 0.3998428756160498}, {"bh": "unit_name", "en": "unit_name", "d": 0.4054725518137876}, {"bh": "dates", "en": "end_date", "d": 0.4403090706655647}], "Template:Refn": [{"bh": "name", "en": "name", "d": 0.21803344649687106}], "Template:Cite book": [{"bh": "location", "en": "location", "d": 0.060850258779650335}, {"bh": "pages", "en": "pages", "d": 0.2532667706021383}, {"bh": "date", "en": "date", "d": 0.25855963384196023}, {"bh": "page", "en": "page", "d": 0.30010879197599183}, {"bh": "url", "en": "url", "d": 0.3011189705043299}, {"bh": "archive-date", "en": "archive-date", "d": 0.3053811047813152}, {"bh": "year", "en": "year", "d": 0.3251210168676537}, {"bh": "archive-url", "en": "archive-url", "d": 0.3316690503994736}, {"bh": "authorlink", "en": "author-link", "d": 0.34029604840680416}, {"bh": "id", "en": "id", "d": 0.3498502040605166}, {"bh": "quote", "en": "quote", "d": 0.3583178396752551}, {"bh": "language", "en": "language", "d": 0.3662079943960146}, {"bh": "format", "en": "format", "d": 0.3769724366771072}, {"bh": "title", "en": "title", "d": 0.40172178962714566}, {"bh": "oclc", "en": "author-link2", "d": 0.4156276334407806}, {"bh": "archivedate", "en": "archiveurl", "d": 0.4165541804745332}, {"bh": "coauthors", "en": "author-last", "d": 0.41825177588650586}, {"bh": "chapter-url", "en": "author3-link", "d": 0.43190589286346803}], "Template:Reflist": [{"bh": "colwidth", "en": "colwidth", "d": 0.4486048646766896}], "Template:Automatic taxobox": [{"bh": "name", "en": "name", "d": 0.21803344649687106}, {"bh": "image", "en": "image", "d": 0.22816033235718702}, {"bh": "image_caption", "en": "image_caption", "d": 0.28013859500029614}, {"bh": "image2", "en": "image2_caption", "d": 0.2936187613447844}, {"bh": "range_map_caption", "en": "range_map_caption", "d": 0.29669515200477414}, {"bh": "diversity_link", "en": "diversity_link", "d": 0.34343653146148034}, {"bh": "image_width", "en": "image_upright", "d": 0.368768891064325}, {"bh": "range_map", "en": "range_map", "d": 0.3719735464900765}, {"bh": "image2_caption", "en": "image_alt", "d": 0.4005054387810085}, {"bh": "type_species_authority", "en": "type_species_authority", "d": 0.40792934793709257}, {"bh": "type_species", "en": "type_species", "d": 0.4149031805622442}, {"bh": "synonyms_ref", "en": "status_ref", "d": 0.42149812975188283}, {"bh": "fossil_range", "en": "range_map_upright", "d": 0.4439237058794867}, {"bh": "synonyms", "en": "synonyms_ref", "d": 0.44643632199761396}, {"bh": "subdivision", "en": "subdivisions", "d": 0.44881962743125003}], "Template:Cite web": [{"bh": "location", "en": "location", "d": 0.060850258779650335}, {"bh": "pages", "en": "pages", "d": 0.2532667706021383}, {"bh": "date", "en": "date", "d": 0.25855963384196023}, {"bh": "page", "en": "page", "d": 0.30010879197599183}, {"bh": "url", "en": "url", "d": 0.3011189705043299}, {"bh": "archive-date", "en": "archive-date", "d": 0.3053811047813152}, {"bh": "year", "en": "year", "d": 0.3251210168676537}, {"bh": "archive-url", "en": "archive-url", "d": 0.3316690503994736}, {"bh": "authorlink", "en": "author-link", "d": 0.34029604840680416}, {"bh": "quote", "en": "quote", "d": 0.3583178396752551}, {"bh": "language", "en": "language", "d": 0.3662079943960146}, {"bh": "format", "en": "format", "d": 0.3769724366771072}, {"bh": "dead-url", "en": "editor-link", "d": 0.3999921753850707}, {"bh": "title", "en": "title", "d": 0.40172178962714566}, {"bh": "archivedate", "en": "archiveurl", "d": 0.4165541804745332}, {"bh": "deadurl", "en": "editor3-link", "d": 0.4249607350977498}, {"bh": "script-title", "en": "script-title", "d": 0.4258456406403509}, {"bh": "archiveurl", "en": "author-link11", "d": 0.4491723649049395}], "Template:Citation": [{"bh": "location", "en": "location", "d": 0.060850258779650335}, {"bh": "pages", "en": "pages", "d": 0.2532667706021383}, {"bh": "date", "en": "date", "d": 0.25855963384196023}, {"bh": "page", "en": "page", "d": 0.30010879197599183}, {"bh": "url", "en": "url", "d": 0.3011189705043299}, {"bh": "archive-date", "en": "archive-date", "d": 0.3053811047813152}, {"bh": "year", "en": "year", "d": 0.3251210168676537}, {"bh": "archive-url", "en": "archive-url", "d": 0.3316690503994736}, {"bh": "authorlink", "en": "author-link", "d": 0.34029604840680416}, {"bh": "quote", "en": "quote", "d": 0.3583178396752551}, {"bh": "author-link", "en": "author3-link", "d": 0.3593215998833619}, {"bh": "language", "en": "language", "d": 0.3662079943960146}, {"bh": "title", "en": "title", "d": 0.40172178962714566}, {"bh": "postscript", "en": "editor3-last", "d": 0.4035316334696083}, {"bh": "archivedate", "en": "archiveurl", "d": 0.4165541804745332}], "Template:Coord": [{"bh": "name", "en": "name", "d": 0.21803344649687106}, {"bh": "format", "en": "format", "d": 0.3769724366771072}], "Template:Infobox video game": [{"bh": "image", "en": "image", "d": 0.22816033235718702}, {"bh": "image_size", "en": "image_size", "d": 0.2591931448675111}, {"bh": "title", "en": "italic title", "d": 0.3680851333469627}], "Template:Infobox settlement": [{"bh": "iso_code", "en": "iso_code", "d": 0.19056109968613721}, {"bh": "image_map", "en": "image_map", "d": 0.20003540186058466}, {"bh": "name", "en": "name", "d": 0.21803344649687106}, {"bh": "image_flag", "en": "image_flag", "d": 0.25232805474573894}, {"bh": "other_name", "en": "other_name", "d": 0.26042190828265943}, {"bh": "pushpin_map", "en": "map_caption1", "d": 0.27353094095084796}, {"bh": "image_skyline", "en": "image_dot_map", "d": 0.279766522283045}, {"bh": "image_caption", "en": "image_caption", "d": 0.28013859500029614}, {"bh": "pushpin_map_caption", "en": "map_caption", "d": 0.2831378529519185}, {"bh": "subdivision_name", "en": "subdivision_name", "d": 0.289268710827983}, {"bh": "map_caption", "en": "dot_map_caption", "d": 0.3031022043306917}, {"bh": "image_shield", "en": "image_alt", "d": 0.3092169254616639}, {"bh": "image_alt", "en": "image_size", "d": 0.31699514461422584}, {"bh": "image_seal", "en": "image_map1", "d": 0.3199668667286206}, {"bh": "native_name", "en": "blank1_name", "d": 0.3374865270705627}, {"bh": "area_code_type", "en": "area_code_type", "d": 0.3407770021162492}, {"bh": "native_name_lang", "en": "blank2_name", "d": 0.34604732251267434}, {"bh": "mapsize", "en": "pushpin_map_size", "d": 0.34692201242100873}, {"bh": "official_name", "en": "official_name", "d": 0.34772498478541236}, {"bh": "coordinates_footnotes", "en": "coordinates_footnotes", "d": 0.3492346810446306}, {"bh": "blank_name", "en": "blank_name", "d": 0.3498524582428505}, {"bh": "pushpin_map_alt", "en": "pushpin_map_caption", "d": 0.35064666609420436}, {"bh": "pushpin_mapsize", "en": "pushpin_map_caption1", "d": 0.3521974107014946}, {"bh": "population_note", "en": "population_note", "d": 0.35529400280645995}, {"bh": "subdivision_type", "en": "subdivision_type", "d": 0.36283056762773}, {"bh": "area_note", "en": "area_note", "d": 0.3704765363756215}, {"bh": "postal_code_type", "en": "postal_code_type", "d": 0.37592484837949447}, {"bh": "subdivision_name3", "en": "subdivision_name5", "d": 0.3759862704769267}, {"bh": "demographics1_title1", "en": "demographics1_title6", "d": 0.37620900947468194}, {"bh": "demographics1_title2", "en": "demographics2_title6", "d": 0.37944352892894295}, {"bh": "subdivision_name1", "en": "subdivision_name4", "d": 0.38232077121944386}, {"bh": "leader_name", "en": "leader_name", "d": 0.38266612791968}, {"bh": "established_date", "en": "established_date", "d": 0.3831820481473779}, {"bh": "subdivision_name2", "en": "subdivision_name2", "d": 0.3909037813988906}, {"bh": "coor_pinpoint", "en": "coor_pinpoint", "d": 0.3943564174897687}, {"bh": "map_alt", "en": "map_alt", "d": 0.39789425166584946}, {"bh": "population_blank1_title", "en": "population_blank2_title", "d": 0.39932993713375975}, {"bh": "population_density_km2", "en": "population_density_blank2_sq_mi", "d": 0.39939529762238857}, {"bh": "population_metro_footnotes", "en": "population_metro_footnotes", "d": 0.4000908856195273}, {"bh": "leader_name2", "en": "blank2_name_sec1", "d": 0.4009747066040492}, {"bh": "subdivision_name4", "en": "subdivision_name1", "d": 0.4012332113643734}, {"bh": "area_code", "en": "area_code", "d": 0.40434732166159193}, {"bh": "area_footnotes", "en": "area_footnotes", "d": 0.40449131312035946}, {"bh": "leader_name1", "en": "blank2_name_sec2", "d": 0.40955577531764975}, {"bh": "imagesize", "en": "image_blank_emblem", "d": 0.4109034894150675}, {"bh": "population_footnotes", "en": "population_footnotes", "d": 0.4145551587659331}, {"bh": "subdivision_type2", "en": "subdivision_type5", "d": 0.414605709671919}, {"bh": "subdivision_type4", "en": "subdivision_type3", "d": 0.41694805891723463}, {"bh": "area_total_sq_mi", "en": "area_blank1_sq_mi", "d": 0.4175747794477477}, {"bh": "area_metro_km2", "en": "area_water_sq_mi", "d": 0.4256202955051702}, {"bh": "coordinates", "en": "coordinates", "d": 0.42879033577169223}, {"bh": "footnotes", "en": "demographics2_footnotes", "d": 0.4308503911335386}, {"bh": "blank3_name_sec1", "en": "blank1_name_sec2", "d": 0.4326301656980627}, {"bh": "subdivision_type3", "en": "subdivision_type4", "d": 0.4345055422205788}, {"bh": "government_footnotes", "en": "government_footnotes", "d": 0.4367929531201137}, {"bh": "subdivision_type1", "en": "subdivision_type2", "d": 0.43698611485676786}, {"bh": "elevation_footnotes", "en": "dimensions_footnotes", "d": 0.43870771848246537}, {"bh": "population_metro", "en": "population_density_metro_sq_mi", "d": 0.4418394588951057}, {"bh": "blank2_name_sec1", "en": "blank_name_sec2", "d": 0.44361302048013296}, {"bh": "utc_offset", "en": "utc_offset_dst", "d": 0.44489700558352807}, {"bh": "blank1_name_sec1", "en": "blank_name_sec1", "d": 0.4460063332982259}, {"bh": "population_urban", "en": "population_density_blank1_sq_mi", "d": 0.44691977904252544}, {"bh": "postal_code", "en": "postal2_code_type", "d": 0.4484864300163415}, {"bh": "utc_offset1", "en": "utc_offset2_dst", "d": 0.44967719052358757}, {"bh": "blank1_name_sec2", "en": "blank1_name_sec1", "d": 0.4498586305574237}], "Template:Use dmy dates": [{"bh": "date", "en": "date", "d": 0.25855963384196023}], "Template:Infobox officeholder": [{"bh": "name", "en": "name", "d": 0.21803344649687106}, {"bh": "image", "en": "image", "d": 0.22816033235718702}, {"bh": "birth_date", "en": "date", "d": 0.28512345377909987}, {"bh": "native_name", "en": "image name", "d": 0.315121320576486}, {"bh": "death_date", "en": "birth_date", "d": 0.36066841242220715}, {"bh": "birth_name", "en": "birth_name", "d": 0.3759942803669367}, {"bh": "term_end", "en": "term_end", "d": 0.39505722060343595}, {"bh": "term_end3", "en": "term_start2", "d": 0.40554911773992164}, {"bh": "term_end1", "en": "term_start3", "d": 0.4175564344188748}, {"bh": "term_end4", "en": "term_start9", "d": 0.4255743607812752}, {"bh": "term_end2", "en": "term_start4", "d": 0.42702531250817133}, {"bh": "footnotes", "en": "footnotes", "d": 0.4351583086810321}, {"bh": "term_end6", "en": "term_start6", "d": 0.44355545739309266}], "Template:Convert": [{"bh": "sortable", "en": "sortable", "d": 0.3820003680816695}], "Template:Start date and age": [], "Template:Infobox film": [{"bh": "name", "en": "name", "d": 0.21803344649687106}, {"bh": "image", "en": "image", "d": 0.22816033235718702}, {"bh": "image size", "en": "image_size", "d": 0.2591931448675111}, {"bh": "country", "en": "country", "d": 0.31025609414271993}, {"bh": "language", "en": "language", "d": 0.3662079943960146}, {"bh": "film name", "en": "native_name", "d": 0.41597032046943716}, {"bh": "image_size", "en": "caption", "d": 0.42355766580283927}, {"bh": "based on", "en": "based_on", "d": 0.448166610820493}], "Template:Film date": [], "Template:Speciesbox": [{"bh": "name", "en": "name", "d": 0.21803344649687106}, {"bh": "image", "en": "image", "d": 0.22816033235718702}, {"bh": "image_upright", "en": "image_caption", "d": 0.27513035752550885}, {"bh": "image2", "en": "image2_caption", "d": 0.2936187613447844}, {"bh": "range_map_caption", "en": "range_map_caption", "d": 0.29669515200477414}, {"bh": "image_caption", "en": "image_alt", "d": 0.36566461062483935}, {"bh": "range_map_alt", "en": "range_map_alt", "d": 0.37109672544474326}, {"bh": "range_map", "en": "range_map", "d": 0.3719735464900765}, {"bh": "synonyms_ref", "en": "status2_ref", "d": 0.3803998134379324}, {"bh": "genus", "en": "taxon", "d": 0.3806198268674623}, {"bh": "image2_caption", "en": "image_upright", "d": 0.40867108523314843}, {"bh": "species", "en": "species", "d": 0.417538146665391}, {"bh": "fossil_range", "en": "range_map_upright", "d": 0.4439237058794867}, {"bh": "synonyms", "en": "synonyms_ref", "d": 0.44643632199761396}], "Template:Cite iucn": [{"bh": "date", "en": "date", "d": 0.25855963384196023}, {"bh": "page", "en": "page", "d": 0.30010879197599183}, {"bh": "year", "en": "year", "d": 0.3251210168676537}, {"bh": "title", "en": "title", "d": 0.40172178962714566}, {"bh": "author2", "en": "author-link", "d": 0.43984486383807386}], "Template:Infobox government agency": [{"bh": "name", "en": "name", "d": 0.21803344649687106}, {"bh": "chief2_name", "en": "deputyminister1_name", "d": 0.3446736923056122}, {"bh": "chief1_name", "en": "deputyminister2_name", "d": 0.35955882663973626}, {"bh": "seal_width", "en": "map_width", "d": 0.361660935075681}, {"bh": "logo_caption", "en": "logo_caption", "d": 0.36272040640654934}, {"bh": "seal_caption", "en": "map_caption", "d": 0.36362910293477624}, {"bh": "logo_width", "en": "logo_width", "d": 0.3734928439377132}, {"bh": "agency_name", "en": "agency_name", "d": 0.3757692383665451}, {"bh": "coordinates", "en": "coordinates", "d": 0.42879033577169223}], "Template:Cite news": [{"bh": "location", "en": "location", "d": 0.060850258779650335}, {"bh": "pages", "en": "pages", "d": 0.2532667706021383}, {"bh": "date", "en": "date", "d": 0.25855963384196023}, {"bh": "page", "en": "page", "d": 0.30010879197599183}, {"bh": "url", "en": "url", "d": 0.3011189705043299}, {"bh": "archive-date", "en": "archive-date", "d": 0.3053811047813152}, {"bh": "archive-url", "en": "archive-url", "d": 0.3316690503994736}, {"bh": "quote", "en": "quote", "d": 0.3583178396752551}, {"bh": "dead-url", "en": "author-link", "d": 0.3614994709428606}, {"bh": "language", "en": "language", "d": 0.3662079943960146}, {"bh": "title", "en": "title", "d": 0.40172178962714566}, {"bh": "archivedate", "en": "archiveurl", "d": 0.4165541804745332}, {"bh": "issn", "en": "author-last", "d": 0.42375778605080716}, {"bh": "deadurl", "en": "author-link2", "d": 0.42903246494712}, {"bh": "trans-title", "en": "script-title", "d": 0.4423612759077826}], "Template:Columns-list": [{"bh": "colwidth", "en": "colwidth", "d": 0.4486048646766896}], "Template:Cite encyclopedia": [{"bh": "location", "en": "location", "d": 0.060850258779650335}, {"bh": "date", "en": "date", "d": 0.25855963384196023}, {"bh": "page", "en": "page", "d": 0.30010879197599183}, {"bh": "url", "en": "url", "d": 0.3011189705043299}, {"bh": "archivedate", "en": "archive-date", "d": 0.3250035585238501}, {"bh": "year", "en": "year", "d": 0.3251210168676537}, {"bh": "archiveurl", "en": "archive-url", "d": 0.33783504287025934}, {"bh": "quote", "en": "quote", "d": 0.3583178396752551}, {"bh": "title", "en": "title", "d": 0.40172178962714566}, {"bh": "encyclopedia", "en": "author-link2", "d": 0.44434957624949567}, {"bh": "author", "en": "author-link", "d": 0.44663424365971305}], "Template:S-bef": [], "Template:S-ttl": [{"bh": "years", "en": "year", "d": 0.39514402354103895}, {"bh": "title", "en": "title", "d": 0.40172178962714566}], "Template:S-aft": [], "Template:Infobox football biography": [], "Template:Birth date and age": [], "Template:Infobox aircraft begin": [{"bh": "name", "en": "name", "d": 0.21803344649687106}, {"bh": "image", "en": "image", "d": 0.22816033235718702}], "Template:Infobox aircraft type": [{"bh": "primary user", "en": "primary user", "d": 0.2984004270781103}, {"bh": "more users", "en": "more users", "d": 0.3999626164619573}, {"bh": "variants with their own articles", "en": "variants with their own articles", "d": 0.40171297532683414}], "Template:Cite magazine": [{"bh": "location", "en": "location", "d": 0.060850258779650335}, {"bh": "date", "en": "date", "d": 0.25855963384196023}, {"bh": "page", "en": "page", "d": 0.30010879197599183}, {"bh": "url", "en": "url", "d": 0.3011189705043299}, {"bh": "language", "en": "language", "d": 0.3662079943960146}, {"bh": "title", "en": "title", "d": 0.40172178962714566}, {"bh": "accessdate", "en": "archive-date", "d": 0.4198339285899523}, {"bh": "trans_title", "en": "script-title", "d": 0.4407223320799558}, {"bh": "author", "en": "author-link", "d": 0.44663424365971305}], "Template:Infobox person": [{"bh": "name", "en": "name", "d": 0.21803344649687106}, {"bh": "image", "en": "image", "d": 0.22816033235718702}, {"bh": "image_size", "en": "image_size", "d": 0.2591931448675111}, {"bh": "imagesize", "en": "image size", "d": 0.3301451936952574}, {"bh": "native_name_lang", "en": "native_name_lang", "d": 0.35075391878927875}, {"bh": "birth_date", "en": "birth_date", "d": 0.35864554242825275}, {"bh": "death_date", "en": "disappeared_date", "d": 0.36530883733648345}, {"bh": "other_names", "en": "other_names", "d": 0.37523073678323615}, {"bh": "other names", "en": "other names", "d": 0.37523073678323615}, {"bh": "birth_name", "en": "birth_name", "d": 0.3759942803669367}, {"bh": "native_name", "en": "native_name", "d": 0.39954854057704536}, {"bh": "title", "en": "title", "d": 0.40172178962714566}, {"bh": "module", "en": "module", "d": 0.4046372111251494}, {"bh": "style", "en": "style", "d": 0.407025967647866}, {"bh": "signature_alt", "en": "image_caption", "d": 0.41449012517017036}, {"bh": "homepage", "en": "url", "d": 0.4256475716947957}, {"bh": "footnotes", "en": "footnotes", "d": 0.4351583086810321}, {"bh": "signature_size", "en": "image_upright", "d": 0.4368922401226163}], "Template:Death date and age": [], "Template:Succession box": [{"bh": "title", "en": "title", "d": 0.40172178962714566}], "Template:Infobox book": [{"bh": "name", "en": "name", "d": 0.21803344649687106}, {"bh": "image", "en": "image", "d": 0.22816033235718702}, {"bh": "pages", "en": "pages", "d": 0.2532667706021383}, {"bh": "image_size", "en": "image_size", "d": 0.2591931448675111}, {"bh": "country", "en": "country", "d": 0.31025609414271993}, {"bh": "language", "en": "language", "d": 0.3662079943960146}, {"bh": "wikisource", "en": "wikisource", "d": 0.4051645310565366}, {"bh": "title_orig", "en": "italic title", "d": 0.41201160949840865}, {"bh": "release_date", "en": "release_date", "d": 0.4239976605273251}, {"bh": "english_pub_date", "en": "english_release_date", "d": 0.4248494799126872}, {"bh": "pub_date", "en": "english_pub_date", "d": 0.4307773238483531}], "Template:Infobox body of water": [{"bh": "location", "en": "location", "d": 0.060850258779650335}, {"bh": "name", "en": "name", "d": 0.21803344649687106}, {"bh": "image", "en": "image", "d": 0.22816033235718702}, {"bh": "other_name", "en": "other_name", "d": 0.26042190828265943}, {"bh": "image_bathymetry", "en": "image_map", "d": 0.2797878052992888}, {"bh": "pushpin_map_caption", "en": "caption_map", "d": 0.2831378529519185}, {"bh": "islands_category", "en": "islands_category", "d": 0.2980372526455438}, {"bh": "sections", "en": "sections", "d": 0.3056941148431723}, {"bh": "pushpin_map", "en": "pushpin_map_caption", "d": 0.3324402644021709}, {"bh": "native_name_lang", "en": "native_name_lang", "d": 0.35075391878927875}, {"bh": "coordinates", "en": "coords", "d": 0.3758311032700169}, {"bh": "alt_bathymetry", "en": "image_size", "d": 0.3937117694317166}, {"bh": "coords", "en": "coordinates_footnotes", "d": 0.3953098015355768}, {"bh": "pushpin_map_alt", "en": "pushpin_map_alt", "d": 0.39832402054804805}, {"bh": "native_name", "en": "native_name", "d": 0.39954854057704536}, {"bh": "etymology", "en": "reference", "d": 0.42325595551839934}, {"bh": "caption_bathymetry", "en": "caption_bathymetry", "d": 0.4263635937787019}, {"bh": "islands", "en": "islands", "d": 0.42807753851260233}, {"bh": "date-flooded", "en": "date-flooded", "d": 0.4481843386255263}], "Template:Dead link": [{"bh": "date", "en": "date", "d": 0.25855963384196023}, {"bh": "bot", "en": "bot", "d": 0.44307554935073423}], "Template:Height": [{"bh": "in", "en": "in", "d": 0.43791905392392516}], "Template:More citations needed": [{"bh": "date", "en": "date", "d": 0.25855963384196023}], "Template:Infobox television channel": [{"bh": "name", "en": "name", "d": 0.21803344649687106}, {"bh": "country", "en": "country", "d": 0.31025609414271993}, {"bh": "picture format", "en": "picture_format", "d": 0.34351094326527465}, {"bh": "language", "en": "language", "d": 0.3662079943960146}, {"bh": "logoalt", "en": "image_size", "d": 0.38787599650183036}, {"bh": "logofile", "en": "image", "d": 0.4021881720126549}], "Template:Infobox organization": [{"bh": "location", "en": "location", "d": 0.060850258779650335}, {"bh": "name", "en": "name", "d": 0.21803344649687106}, {"bh": "image", "en": "image", "d": 0.22816033235718702}, {"bh": "map", "en": "map", "d": 0.29663798607129965}, {"bh": "language", "en": "language", "d": 0.3662079943960146}, {"bh": "leader_name", "en": "leader_name", "d": 0.38266612791968}, {"bh": "size", "en": "image_size", "d": 0.4033520265352766}, {"bh": "msize", "en": "logo_size", "d": 0.4081097930285007}, {"bh": "mcaption", "en": "location_city2", "d": 0.4255656647112628}, {"bh": "caption", "en": "map_caption", "d": 0.4387221693035368}], "Template:Infobox school": [{"bh": "name", "en": "name", "d": 0.21803344649687106}, {"bh": "image", "en": "image", "d": 0.22816033235718702}, {"bh": "country", "en": "country", "d": 0.31025609414271993}, {"bh": "caption", "en": "location", "d": 0.40228095343102854}, {"bh": "coordinates", "en": "coordinates", "d": 0.42879033577169223}], "Template:Color box": [], "Template:Birth date": [], "Template:Infobox military installation": [], "Template:Cite press release": [{"bh": "location", "en": "location", "d": 0.060850258779650335}, {"bh": "date", "en": "date", "d": 0.25855963384196023}, {"bh": "url", "en": "url", "d": 0.3011189705043299}, {"bh": "archive-date", "en": "archive-date", "d": 0.3053811047813152}, {"bh": "archive-url", "en": "archive-url", "d": 0.3316690503994736}, {"bh": "language", "en": "language", "d": 0.3662079943960146}, {"bh": "title", "en": "title", "d": 0.40172178962714566}, {"bh": "archivedate", "en": "archiveurl", "d": 0.4165541804745332}, {"bh": "archiveurl", "en": "author-link", "d": 0.44001558823707176}, {"bh": "trans-title", "en": "script-title", "d": 0.4423612759077826}], "Template:Navboxes": [{"bh": "list", "en": "list", "d": 0.2106935456009802}, {"bh": "title", "en": "title", "d": 0.40172178962714566}, {"bh": "list1", "en": "list1", "d": 0.4209016288490872}], "Template:Infobox artist": [{"bh": "name", "en": "name", "d": 0.21803344649687106}, {"bh": "image", "en": "image", "d": 0.22816033235718702}, {"bh": "image_size", "en": "image_size", "d": 0.2591931448675111}, {"bh": "birth_date", "en": "birth_date", "d": 0.35864554242825275}, {"bh": "birth_name", "en": "birth_name", "d": 0.3759942803669367}, {"bh": "death_date", "en": "death_date", "d": 0.3870147463492204}], "Template:Multiple image": [{"bh": "background color", "en": "background color", "d": 0.2762581333513534}, {"bh": "image8", "en": "image5", "d": 0.35067147249419994}, {"bh": "footer_background", "en": "header_background", "d": 0.351277973733891}, {"bh": "image1", "en": "image9", "d": 0.36081489984131365}, {"bh": "image4", "en": "image3", "d": 0.363421395764817}, {"bh": "image3", "en": "image7", "d": 0.3797158323261093}, {"bh": "footer_align", "en": "footer_align", "d": 0.38120488432848487}, {"bh": "header", "en": "header", "d": 0.3824643576676716}, {"bh": "image7", "en": "image6", "d": 0.38368886949929715}, {"bh": "image6", "en": "image8", "d": 0.3895027568739843}, {"bh": "image5", "en": "image4", "d": 0.3938799379157807}, {"bh": "image2", "en": "image1", "d": 0.3959115968110992}, {"bh": "caption_align", "en": "caption_align", "d": 0.40423391720543234}, {"bh": "footer", "en": "footer_background", "d": 0.437441524313512}], "Template:Infobox song": [{"bh": "name", "en": "name", "d": 0.21803344649687106}, {"bh": "language", "en": "language", "d": 0.3662079943960146}, {"bh": "format", "en": "format", "d": 0.3769724366771072}], "Template:Duration": [], "Template:External music video": [], "Template:Infobox artwork": [{"bh": "image_file", "en": "image_file", "d": 0.2195733848355177}, {"bh": "image_size", "en": "image_size", "d": 0.2591931448675111}, {"bh": "year", "en": "year", "d": 0.3251210168676537}, {"bh": "title", "en": "italic title", "d": 0.3680851333469627}, {"bh": "width_imperial", "en": "map_size", "d": 0.3862955967898478}, {"bh": "width_metric", "en": "width_metric", "d": 0.4292947994825521}], "Template:Start date": [], "Template:Infobox cricketer": [{"bh": "name", "en": "name", "d": 0.21803344649687106}, {"bh": "image", "en": "image", "d": 0.22816033235718702}, {"bh": "date", "en": "date", "d": 0.25855963384196023}, {"bh": "source", "en": "source", "d": 0.3030344350699311}, {"bh": "country", "en": "country", "d": 0.31025609414271993}, {"bh": "year", "en": "year", "d": 0.3251210168676537}, {"bh": "birth_date", "en": "birth_date", "d": 0.35864554242825275}, {"bh": "fullname", "en": "full_name", "d": 0.40147177264982425}, {"bh": "top score3", "en": "top score1", "d": 0.40700250346491773}, {"bh": "top score4", "en": "top score3", "d": 0.4247088284693782}, {"bh": "top score2", "en": "top score4", "d": 0.4253086998581992}, {"bh": "t20idebutdate", "en": "death_date", "d": 0.4328599942147966}, {"bh": "top score1", "en": "top score2", "d": 0.4476265212145172}], "Template:Infobox magazine": [{"bh": "category", "en": "category", "d": 0.15120470121779528}, {"bh": "image_file", "en": "image_file", "d": 0.2195733848355177}, {"bh": "image_size", "en": "image_size", "d": 0.2591931448675111}, {"bh": "image_caption", "en": "image_caption", "d": 0.28013859500029614}, {"bh": "image_alt", "en": "image", "d": 0.2993187150794987}, {"bh": "country", "en": "country", "d": 0.31025609414271993}, {"bh": "language", "en": "language", "d": 0.3662079943960146}, {"bh": "logo_size", "en": "logo_size", "d": 0.382559244531926}, {"bh": "title", "en": "title", "d": 0.40172178962714566}, {"bh": "editor_title", "en": "editor_title2", "d": 0.41845566404219203}], "Template:Infobox musical artist": [{"bh": "name", "en": "name", "d": 0.21803344649687106}, {"bh": "image", "en": "image", "d": 0.22816033235718702}, {"bh": "image_size", "en": "image_size", "d": 0.2591931448675111}, {"bh": "birth_date", "en": "birth_date", "d": 0.35864554242825275}, {"bh": "birth_name", "en": "birth_name", "d": 0.3759942803669367}, {"bh": "death_date", "en": "death_date", "d": 0.3870147463492204}, {"bh": "native_name", "en": "native_name", "d": 0.39954854057704536}, {"bh": "website", "en": "url", "d": 0.44537087370342054}], "Template:Div col": [{"bh": "content", "en": "content", "d": 0.40575085898989305}, {"bh": "style", "en": "style", "d": 0.407025967647866}, {"bh": "colwidth", "en": "colwidth", "d": 0.4486048646766896}], "Template:Webarchive": [{"bh": "date", "en": "date", "d": 0.25855963384196023}, {"bh": "url", "en": "url", "d": 0.3011189705043299}, {"bh": "language", "en": "language", "d": 0.3662079943960146}, {"bh": "title", "en": "title", "d": 0.40172178962714566}], "Template:Sfn": [{"bh": "page", "en": "page", "d": 0.30010879197599183}], "Template:Sfnm": [], "Template:Refbegin": [{"bh": "colwidth", "en": "colwidth", "d": 0.4486048646766896}], "Template:Subject bar": [{"bh": "commons-search", "en": "wikt-search", "d": 0.432203992525094}, {"bh": "commons", "en": "commons", "d": 0.4465532368493681}], "Template:Infobox university": [{"bh": "image_name", "en": "image_name", "d": 0.19319794457156225}, {"bh": "name", "en": "name", "d": 0.21803344649687106}, {"bh": "image", "en": "image", "d": 0.22816033235718702}, {"bh": "image_size", "en": "image_size", "d": 0.2591931448675111}, {"bh": "country", "en": "country", "d": 0.31025609414271993}, {"bh": "other", "en": "other", "d": 0.34007514645099013}, {"bh": "latin_name", "en": "latin_name", "d": 0.3692048889228463}, {"bh": "native_name", "en": "other_name", "d": 0.389129278040272}, {"bh": "caption", "en": "location", "d": 0.40228095343102854}, {"bh": "free_label", "en": "free_label", "d": 0.4043564943233767}, {"bh": "footnotes", "en": "footnotes", "d": 0.4351583086810321}], "Template:Chembox": [{"bh": "iupacname", "en": "name", "d": 0.362190302233241}, {"bh": "verifiedrevid", "en": "verifiedfields", "d": 0.4108239987884763}, {"bh": "watchedfields", "en": "imagefile_ref", "d": 0.4417366999412826}], "Template:Infobox writer": [{"bh": "name", "en": "name", "d": 0.21803344649687106}, {"bh": "image", "en": "image", "d": 0.22816033235718702}, {"bh": "image_size", "en": "image_size", "d": 0.2591931448675111}, {"bh": "image_upright", "en": "image_upright", "d": 0.32083451441246846}, {"bh": "native_name_lang", "en": "native_name_lang", "d": 0.35075391878927875}, {"bh": "birth_date", "en": "birth_date", "d": 0.35864554242825275}, {"bh": "language", "en": "language", "d": 0.3662079943960146}, {"bh": "birth_name", "en": "birth_name", "d": 0.3759942803669367}, {"bh": "death_date", "en": "death_date", "d": 0.3870147463492204}, {"bh": "native_name", "en": "native_name", "d": 0.39954854057704536}, {"bh": "module", "en": "module", "d": 0.4046372111251494}], "Template:Historical populations": [{"bh": "footnote", "en": "footnote", "d": 0.4051127547033557}], "Template:Infobox station": [{"bh": "name", "en": "name", "d": 0.21803344649687106}, {"bh": "image", "en": "image", "d": 0.22816033235718702}, {"bh": "image_size", "en": "image_size", "d": 0.2591931448675111}, {"bh": "image_caption", "en": "image_caption", "d": 0.28013859500029614}, {"bh": "map_locator", "en": "map_locator", "d": 0.3081354944053444}, {"bh": "country", "en": "country", "d": 0.31025609414271993}, {"bh": "other", "en": "other", "d": 0.34007514645099013}, {"bh": "map_type", "en": "map_type", "d": 0.36125044153877994}, {"bh": "code", "en": "code", "d": 0.37987622405765586}, {"bh": "style", "en": "style", "d": 0.407025967647866}, {"bh": "entrances", "en": "other_services2_header", "d": 0.4218829722078983}, {"bh": "baggage_check", "en": "mapframe-caption", "d": 0.42410131461708045}, {"bh": "elevation", "en": "symbol_location", "d": 0.4281558879595968}, {"bh": "coordinates", "en": "coordinates", "d": 0.42879033577169223}, {"bh": "pass_percent", "en": "map_size", "d": 0.43279798112518675}], "Template:Infobox mapframe": [{"bh": "wikidata", "en": "wikidata", "d": 0.20550034057174682}], "Template:Infobox television": [{"bh": "location", "en": "location", "d": 0.060850258779650335}, {"bh": "name", "en": "name", "d": 0.21803344649687106}, {"bh": "image", "en": "image", "d": 0.22816033235718702}, {"bh": "image_size", "en": "image_size", "d": 0.2591931448675111}, {"bh": "country", "en": "country", "d": 0.31025609414271993}, {"bh": "picture_format", "en": "picture_format", "d": 0.34351094326527465}, {"bh": "image_alt", "en": "image_alt", "d": 0.3435627961519965}, {"bh": "language", "en": "language", "d": 0.3662079943960146}, {"bh": "audio_format", "en": "audio_format", "d": 0.3681834361782006}, {"bh": "website_title", "en": "italic_title", "d": 0.42264613418720565}, {"bh": "show_name", "en": "alt_name", "d": 0.4478628768962083}, {"bh": "based_on", "en": "based_on", "d": 0.448166610820493}, {"bh": "list_episodes", "en": "list_episodes", "d": 0.44906186479414245}], "Template:Post-nominals": [{"bh": "list", "en": "list", "d": 0.2106935456009802}, {"bh": "country", "en": "country", "d": 0.31025609414271993}], "Template:Infobox ship image": [{"bh": "ship image", "en": "image", "d": 0.3255820525252958}, {"bh": "ship caption", "en": "ship image size", "d": 0.3754691909763427}], "Template:Infobox ship career": [{"bh": "ship name", "en": "ship name", "d": 0.35314085538883433}, {"bh": "ship country", "en": "ship country", "d": 0.3759703592496805}, {"bh": "hide header", "en": "hide header", "d": 0.39011280569150275}, {"bh": "ship decommissioned", "en": "ship way number", "d": 0.4124214008774387}, {"bh": "ship flag", "en": "ship flag", "d": 0.4251057686956272}], "Template:Infobox ship characteristics": [{"bh": "header caption", "en": "header caption", "d": 0.342205101496851}, {"bh": "hide header", "en": "hide header", "d": 0.39011280569150275}, {"bh": "ship time to activate", "en": "ship time to activate", "d": 0.3917074913354025}], "Template:Infobox military person": [], "Template:Librivox author": [{"bh": "id", "en": "id", "d": 0.3498502040605166}], "Template:Infobox religious biography": [{"bh": "name", "en": "name", "d": 0.21803344649687106}, {"bh": "image", "en": "image", "d": 0.22816033235718702}, {"bh": "other_names", "en": "other_name", "d": 0.34179163377019317}, {"bh": "birth_date", "en": "birth_date", "d": 0.35864554242825275}, {"bh": "birth_name", "en": "birth_name", "d": 0.3759942803669367}, {"bh": "death_date", "en": "death_date", "d": 0.3870147463492204}, {"bh": "caption", "en": "location", "d": 0.40228095343102854}], "Template:Infobox political party": [], "Template:Infobox badminton player": [], "Template:Cbignore": [{"bh": "bot", "en": "bot", "d": 0.44307554935073423}], "Template:Flag": [{"bh": "name", "en": "name", "d": 0.21803344649687106}], "Template:Infobox royalty": [{"bh": "name", "en": "name", "d": 0.21803344649687106}, {"bh": "image", "en": "image", "d": 0.22816033235718702}, {"bh": "full name", "en": "full name", "d": 0.34377531239682224}, {"bh": "birth_date", "en": "birth_date", "d": 0.35864554242825275}, {"bh": "birth_name", "en": "birth_name", "d": 0.3759942803669367}, {"bh": "death_date", "en": "death_date", "d": 0.3870147463492204}, {"bh": "title", "en": "title", "d": 0.40172178962714566}], "Template:Legend": [], "Template:Infobox ethnic group": [{"bh": "image", "en": "image", "d": 0.22816033235718702}, {"bh": "languages", "en": "languages", "d": 0.3582518186549172}], "Template:Infobox writing system": [{"bh": "name", "en": "name", "d": 0.21803344649687106}, {"bh": "languages", "en": "languages", "d": 0.3582518186549172}, {"bh": "unicode", "en": "unicode", "d": 0.3821632511558636}], "Template:Location map many": [{"bh": "float", "en": "marksize", "d": 0.4430929274458507}], "Template:Infobox company": [{"bh": "location", "en": "location", "d": 0.060850258779650335}, {"bh": "location_country", "en": "location_country", "d": 0.17711557266432254}, {"bh": "name", "en": "name", "d": 0.21803344649687106}, {"bh": "image", "en": "image", "d": 0.22816033235718702}, {"bh": "hq_location_country", "en": "hq_location_country", "d": 0.23660275446090573}, {"bh": "hq_location", "en": "location_city", "d": 0.23724227744300752}, {"bh": "image_size", "en": "image_size", "d": 0.2591931448675111}, {"bh": "image_caption", "en": "image_caption", "d": 0.28013859500029614}, {"bh": "locations", "en": "hq_location", "d": 0.32016175661425483}, {"bh": "hq_location_city", "en": "hq_location_city", "d": 0.3213134243258783}, {"bh": "logo_caption", "en": "logo_caption", "d": 0.36272040640654934}, {"bh": "logo_size", "en": "logo_size", "d": 0.382559244531926}, {"bh": "native_name", "en": "native_name", "d": 0.39954854057704536}, {"bh": "footnotes", "en": "footnotes", "d": 0.4351583086810321}], "Template:Infobox academic": [{"bh": "name", "en": "name", "d": 0.21803344649687106}, {"bh": "image", "en": "image", "d": 0.22816033235718702}], "Template:Infobox tennis biography": [{"bh": "name", "en": "name", "d": 0.21803344649687106}, {"bh": "image", "en": "image", "d": 0.22816033235718702}, {"bh": "country", "en": "country", "d": 0.31025609414271993}, {"bh": "birth_date", "en": "birth_date", "d": 0.35864554242825275}, {"bh": "fullname", "en": "itf_name", "d": 0.3931113130584145}], "Template:When": [{"bh": "date", "en": "date", "d": 0.25855963384196023}], "Template:Death date": [], "Template:Marriage": [{"bh": "end", "en": "end", "d": 0.43538968368728337}], "Template:Jct": [{"bh": "country", "en": "country", "d": 0.31025609414271993}], "Template:Infobox river": [{"bh": "source1_location", "en": "source2_location", "d": 0.16685690355362093}, {"bh": "mouth_location", "en": "location", "d": 0.17296796603691733}, {"bh": "name", "en": "name", "d": 0.21803344649687106}, {"bh": "image", "en": "image", "d": 0.22816033235718702}, {"bh": "image_size", "en": "image_size", "d": 0.2591931448675111}, {"bh": "name_other", "en": "name_other", "d": 0.26042190828265943}, {"bh": "image_caption", "en": "image_caption", "d": 0.28013859500029614}, {"bh": "pushpin_map_caption", "en": "map_caption", "d": 0.2831378529519185}, {"bh": "discharge1_location", "en": "source1_location", "d": 0.291364700317419}, {"bh": "source1_elevation", "en": "source_confluence_location", "d": 0.29392823167256865}, {"bh": "map", "en": "map", "d": 0.29663798607129965}, {"bh": "pushpin_map_size", "en": "map_size", "d": 0.31349278225884236}, {"bh": "source1_coordinates", "en": "source_confluence_coordinates", "d": 0.3183717982870965}, {"bh": "map_caption", "en": "pushpin_map_caption", "d": 0.32937702302714733}, {"bh": "name_native_lang", "en": "name_native_lang", "d": 0.35075391878927875}, {"bh": "name_etymology", "en": "name_etymology", "d": 0.3516473264218086}, {"bh": "pushpin_map", "en": "map_alt", "d": 0.35234690723723416}, {"bh": "map_size", "en": "pushpin_map_size", "d": 0.3542596686261078}, {"bh": "source1", "en": "source_confluence", "d": 0.370174445671837}, {"bh": "custom_data", "en": "custom_data", "d": 0.37130716027500976}, {"bh": "subdivision_name3", "en": "subdivision_name5", "d": 0.3759862704769267}, {"bh": "mouth_elevation", "en": "discharge1_location", "d": 0.37835430087158206}, {"bh": "subdivision_name1", "en": "subdivision_name4", "d": 0.38232077121944386}, {"bh": "name_native", "en": "other_name", "d": 0.389129278040272}, {"bh": "subdivision_name2", "en": "subdivision_name2", "d": 0.3909037813988906}, {"bh": "subdivision_name4", "en": "subdivision_name1", "d": 0.4012332113643734}, {"bh": "subdivision_name5", "en": "subdivision_name3", "d": 0.4022892254737723}, {"bh": "subdivision_type2", "en": "subdivision_type5", "d": 0.414605709671919}, {"bh": "subdivision_type4", "en": "subdivision_type3", "d": 0.41694805891723463}, {"bh": "subdivision_type3", "en": "subdivision_type4", "d": 0.4345055422205788}, {"bh": "map_alt", "en": "pushpin_map_alt", "d": 0.43632184905746885}, {"bh": "subdivision_type1", "en": "subdivision_type2", "d": 0.43698611485676786}, {"bh": "mouth_coordinates", "en": "mouth_coord_ref", "d": 0.4451271868802248}, {"bh": "custom_label", "en": "custom_label", "d": 0.4494174634215363}], "Template:Clarify": [{"bh": "date", "en": "date", "d": 0.25855963384196023}], "Template:Cite report": [{"bh": "location", "en": "location", "d": 0.060850258779650335}, {"bh": "date", "en": "date", "d": 0.25855963384196023}, {"bh": "page", "en": "page", "d": 0.30010879197599183}, {"bh": "url", "en": "url", "d": 0.3011189705043299}, {"bh": "archive-date", "en": "archive-date", "d": 0.3053811047813152}, {"bh": "year", "en": "year", "d": 0.3251210168676537}, {"bh": "archive-url", "en": "archive-url", "d": 0.3316690503994736}, {"bh": "quote", "en": "quote", "d": 0.3583178396752551}, {"bh": "language", "en": "language", "d": 0.3662079943960146}, {"bh": "chapter-url", "en": "author-link", "d": 0.387980128431348}, {"bh": "title", "en": "title", "d": 0.40172178962714566}], "Template:Infobox rail line": [], "Template:Infobox sportsperson": [{"bh": "name", "en": "name", "d": 0.21803344649687106}, {"bh": "image", "en": "image", "d": 0.22816033235718702}, {"bh": "image_size", "en": "image_size", "d": 0.2591931448675111}, {"bh": "country", "en": "country", "d": 0.31025609414271993}, {"bh": "birth_date", "en": "birth_date", "d": 0.35864554242825275}], "Template:Infobox canal": [], "Template:Singles": [{"bh": "name", "en": "name", "d": 0.21803344649687106}, {"bh": "single 1 date", "en": "single9date", "d": 0.43774055636320375}], "Template:Infobox football club": [{"bh": "image", "en": "image", "d": 0.22816033235718702}, {"bh": "fullname", "en": "short name", "d": 0.4493606353837961}], "Template:Plainlist": [{"bh": "style", "en": "style", "d": 0.407025967647866}], "Template:Infobox building": [{"bh": "location", "en": "location", "d": 0.060850258779650335}, {"bh": "name", "en": "name", "d": 0.21803344649687106}, {"bh": "image", "en": "image", "d": 0.22816033235718702}, {"bh": "completion_date", "en": "closing_date", "d": 0.3442615436025759}, {"bh": "start_date", "en": "start_date", "d": 0.34655123607344285}, {"bh": "map_type", "en": "map_type", "d": 0.36125044153877994}, {"bh": "other_dimensions", "en": "other_dimensions", "d": 0.3974417989965132}, {"bh": "coordinates", "en": "coordinates", "d": 0.42879033577169223}, {"bh": "caption", "en": "map_caption", "d": 0.4387221693035368}], "Template:Infobox weapon": [], "Template:Efn": [{"bh": "name", "en": "name", "d": 0.21803344649687106}], "Template:Fix": [{"bh": "text", "en": "text", "d": 0.3534042633471749}], "Template:Infobox military conflict": [{"bh": "image", "en": "image", "d": 0.22816033235718702}, {"bh": "date", "en": "date", "d": 0.25855963384196023}, {"bh": "image_size", "en": "image_size", "d": 0.2591931448675111}, {"bh": "map_marksize", "en": "map_marksize", "d": 0.2639646073261771}, {"bh": "map_label", "en": "map_label", "d": 0.2819811586459252}, {"bh": "map_relief", "en": "map_caption", "d": 0.2855236338944168}, {"bh": "map_size", "en": "map_size", "d": 0.32857035188980477}, {"bh": "map_type", "en": "map_type", "d": 0.36125044153877994}, {"bh": "coordinates", "en": "coordinates", "d": 0.42879033577169223}, {"bh": "map_caption", "en": "caption", "d": 0.4484699175408784}], "Template:Age in years, months, weeks and days": [{"bh": "year1", "en": "year", "d": 0.3339704651572655}], "Template:Election box begin": [{"bh": "title", "en": "title", "d": 0.40172178962714566}], "Template:Election box candidate with party link": [], "Template:Election box majority": [], "Template:Election box turnout": [], "Template:Election box new seat win": [], "Template:Election box candidate": [], "Template:Maplink": [{"bh": "id", "en": "id", "d": 0.3498502040605166}, {"bh": "text", "en": "text", "d": 0.3534042633471749}, {"bh": "title", "en": "title", "d": 0.40172178962714566}, {"bh": "stroke-width", "en": "frame-width", "d": 0.4079911955350992}, {"bh": "frame-height", "en": "frame-height", "d": 0.43898087872338076}], "Template:Sister project links": [{"bh": "species", "en": "species", "d": 0.417538146665391}, {"bh": "commons", "en": "commons", "d": 0.4465532368493681}], "Template:Infobox museum": [{"bh": "location", "en": "location", "d": 0.060850258779650335}, {"bh": "name", "en": "name", "d": 0.21803344649687106}, {"bh": "image", "en": "image", "d": 0.22816033235718702}, {"bh": "map_relief", "en": "map_caption", "d": 0.2855236338944168}, {"bh": "map_size", "en": "map_size", "d": 0.32857035188980477}, {"bh": "imagesize", "en": "image_size", "d": 0.3301451936952574}, {"bh": "native_name_lang", "en": "native_name_lang", "d": 0.35075391878927875}, {"bh": "map_type", "en": "map_type", "d": 0.36125044153877994}, {"bh": "map_caption", "en": "map_alt", "d": 0.38718336766624173}, {"bh": "native_name", "en": "native_name", "d": 0.39954854057704536}, {"bh": "map_alt", "en": "logo_caption", "d": 0.41299203849183286}, {"bh": "coordinates", "en": "coordinates", "d": 0.42879033577169223}], "Template:Val": [], "Template:Cite episode": [{"bh": "date", "en": "date", "d": 0.25855963384196023}, {"bh": "url", "en": "url", "d": 0.3011189705043299}, {"bh": "number", "en": "number", "d": 0.3859289249514911}, {"bh": "serieslink", "en": "author-link", "d": 0.38723810688811244}, {"bh": "title", "en": "title", "d": 0.40172178962714566}, {"bh": "station", "en": "location", "d": 0.4050857125772004}, {"bh": "accessdate", "en": "archive-date", "d": 0.4198339285899523}], "Template:Infobox holiday": [{"bh": "image", "en": "image", "d": 0.22816033235718702}, {"bh": "date", "en": "date", "d": 0.25855963384196023}, {"bh": "image_size", "en": "image_size", "d": 0.2591931448675111}, {"bh": "official_name", "en": "official_name", "d": 0.34772498478541236}, {"bh": "holiday_name", "en": "holiday_name", "d": 0.38192832407636745}, {"bh": "litcolor", "en": "litcolor", "d": 0.4399930646702094}], "Template:Infobox historic site": [{"bh": "location", "en": "location", "d": 0.060850258779650335}, {"bh": "name", "en": "name", "d": 0.21803344649687106}, {"bh": "image", "en": "image", "d": 0.22816033235718702}, {"bh": "image_size", "en": "image_size", "d": 0.2591931448675111}, {"bh": "designation2_date", "en": "designation2_date", "d": 0.26956949431671406}, {"bh": "designation3_date", "en": "designation1_date", "d": 0.28063677994940395}, {"bh": "designation1_date", "en": "designation5_date", "d": 0.28326609489676546}, {"bh": "map_caption", "en": "map_caption", "d": 0.28735827570663164}, {"bh": "designation4_date", "en": "designation3_date", "d": 0.2945372061659316}, {"bh": "designation3_number", "en": "designation2_number", "d": 0.2977631092805961}, {"bh": "designation1_number", "en": "designation1_number", "d": 0.31247736229631995}, {"bh": "designation1_free1name", "en": "designation2_free1name", "d": 0.34820682429196004}, {"bh": "designation1_free2name", "en": "designation1_free1name", "d": 0.36191037035737306}, {"bh": "designation1_free1value", "en": "designation2_free2value", "d": 0.3663916203756903}, {"bh": "designation1_free2value", "en": "designation2_free3value", "d": 0.37905298896212014}, {"bh": "designation1_type", "en": "designation2_type", "d": 0.3827077719347364}, {"bh": "locmapin", "en": "map_width", "d": 0.3853636089043134}, {"bh": "designation1_offname", "en": "designation5_number", "d": 0.39308491795521394}, {"bh": "designation1_criteria", "en": "designation2_criteria", "d": 0.3955530373493831}, {"bh": "coordinates", "en": "coordinates", "d": 0.42879033577169223}, {"bh": "visitation_num", "en": "designation3_number", "d": 0.4321186557239626}], "Template:Infobox mobile phone": [{"bh": "name", "en": "name", "d": 0.21803344649687106}, {"bh": "image", "en": "image", "d": 0.22816033235718702}, {"bh": "other", "en": "other", "d": 0.34007514645099013}], "Template:Collapsible list": [{"bh": "liststyle", "en": "liststyle", "d": 0.39169074133274295}, {"bh": "titlestyle", "en": "title_style", "d": 0.39647090292293874}, {"bh": "title", "en": "title", "d": 0.40172178962714566}], "Template:Infobox cultivar": [{"bh": "name", "en": "name", "d": 0.21803344649687106}, {"bh": "image", "en": "image", "d": 0.22816033235718702}, {"bh": "image_caption", "en": "image_caption", "d": 0.28013859500029614}, {"bh": "genus", "en": "species", "d": 0.41650157970903623}], "Template:Infobox road": [{"bh": "image", "en": "image", "d": 0.22816033235718702}, {"bh": "map", "en": "map", "d": 0.29663798607129965}, {"bh": "country", "en": "country", "d": 0.31025609414271993}, {"bh": "image_notes", "en": "image_notes", "d": 0.3494200066280727}, {"bh": "map_custom", "en": "map_alot", "d": 0.3728268716353714}, {"bh": "map_notes", "en": "map_notes", "d": 0.3994227413252518}, {"bh": "next_type", "en": "header_type", "d": 0.4127582975120272}, {"bh": "states", "en": "states", "d": 0.41726384269785854}], "Template:Cite map": [{"bh": "date", "en": "date", "d": 0.25855963384196023}, {"bh": "page", "en": "page", "d": 0.30010879197599183}, {"bh": "url", "en": "url", "d": 0.3011189705043299}, {"bh": "archive-date", "en": "archive-date", "d": 0.3053811047813152}, {"bh": "year", "en": "year", "d": 0.3251210168676537}, {"bh": "archive-url", "en": "archive-url", "d": 0.3316690503994736}, {"bh": "format", "en": "format", "d": 0.3769724366771072}, {"bh": "title", "en": "title", "d": 0.40172178962714566}], "Template:Infobox clergy": [], "Template:Infobox comedian": [{"bh": "name", "en": "name", "d": 0.21803344649687106}, {"bh": "image", "en": "image", "d": 0.22816033235718702}, {"bh": "birth_date", "en": "birth_date", "d": 0.35864554242825275}, {"bh": "birth_name", "en": "birth_name", "d": 0.3759942803669367}, {"bh": "module", "en": "module", "d": 0.4046372111251494}, {"bh": "medium", "en": "image_size", "d": 0.43245104514238475}], "Template:Infobox": [{"bh": "image", "en": "image", "d": 0.22816033235718702}, {"bh": "data5", "en": "data11", "d": 0.39077023603376415}, {"bh": "data1", "en": "data12", "d": 0.4144600224199134}, {"bh": "data6", "en": "data9", "d": 0.42496336634187193}, {"bh": "data4", "en": "data1", "d": 0.43609209582758257}, {"bh": "data2", "en": "data15", "d": 0.440436619071198}], "Template:Infobox library": [{"bh": "location", "en": "location", "d": 0.060850258779650335}, {"bh": "name", "en": "name", "d": 0.21803344649687106}, {"bh": "image", "en": "image", "d": 0.22816033235718702}, {"bh": "country", "en": "country", "d": 0.31025609414271993}, {"bh": "library_name", "en": "library_name", "d": 0.32646948293048283}, {"bh": "name_en", "en": "name_en", "d": 0.3297840787266485}, {"bh": "caption", "en": "location_map", "d": 0.4034200189446221}, {"bh": "collection_size", "en": "image_size", "d": 0.4120968399874847}, {"bh": "req_to_access", "en": "req_to_access", "d": 0.41749312588392595}, {"bh": "library_logo", "en": "library_logo", "d": 0.4186776488521178}, {"bh": "ref_legal_mandate", "en": "ref_legal_mandate", "d": 0.42575309779578396}, {"bh": "coordinates", "en": "coordinates", "d": 0.42879033577169223}], "Template:Infobox website": [{"bh": "location", "en": "location", "d": 0.060850258779650335}, {"bh": "name", "en": "name", "d": 0.21803344649687106}, {"bh": "url", "en": "url", "d": 0.3011189705043299}, {"bh": "language", "en": "language_footnote", "d": 0.3170475972912056}, {"bh": "collapsible", "en": "collapsible", "d": 0.37078248690930893}, {"bh": "logo_size", "en": "logo_size", "d": 0.382559244531926}, {"bh": "launch date", "en": "launch_date", "d": 0.4001922708880141}, {"bh": "logo", "en": "logo_caption", "d": 0.4482412897463559}], "Template:Infobox protected area": [{"bh": "location", "en": "location", "d": 0.060850258779650335}, {"bh": "name", "en": "name", "d": 0.21803344649687106}, {"bh": "iucn_category", "en": "iucn_category", "d": 0.25654572731955316}, {"bh": "map_caption", "en": "map_caption", "d": 0.28735827570663164}, {"bh": "map", "en": "map", "d": 0.29663798607129965}, {"bh": "url", "en": "url", "d": 0.3011189705043299}, {"bh": "map_width", "en": "map_width", "d": 0.3033451446684897}, {"bh": "map_alt", "en": "map_image", "d": 0.3201422695360432}, {"bh": "photo_caption", "en": "image_map", "d": 0.3386315130985632}, {"bh": "alt_name", "en": "alt_name", "d": 0.35860196861906335}, {"bh": "coords_ref", "en": "coords_ref", "d": 0.36253729977056703}, {"bh": "photo_width", "en": "photo_width", "d": 0.3747475905998682}, {"bh": "coordinates", "en": "coords", "d": 0.3758311032700169}, {"bh": "world_heritage_site", "en": "world_heritage_site", "d": 0.39935094902538815}, {"bh": "relief", "en": "map_alt", "d": 0.4289558371415362}, {"bh": "area_acre", "en": "area_sqmi", "d": 0.44190730186237215}, {"bh": "visitation_num", "en": "map_size", "d": 0.443884741548883}, {"bh": "coords", "en": "coordinates", "d": 0.44392629251357896}], "Template:Cite tweet": [{"bh": "user", "en": "user", "d": 0.014104321525090224}, {"bh": "date", "en": "date", "d": 0.25855963384196023}, {"bh": "archivedate", "en": "archive-date", "d": 0.3250035585238501}, {"bh": "archiveurl", "en": "archive-url", "d": 0.33783504287025934}, {"bh": "deadurl", "en": "author-link", "d": 0.3721114321804214}, {"bh": "number", "en": "number", "d": 0.3859289249514911}, {"bh": "title", "en": "title", "d": 0.40172178962714566}], "Template:Composition bar": [], "Template:Cite conference": [{"bh": "location", "en": "location", "d": 0.060850258779650335}, {"bh": "pages", "en": "pages", "d": 0.2532667706021383}, {"bh": "date", "en": "date", "d": 0.25855963384196023}, {"bh": "url", "en": "url", "d": 0.3011189705043299}, {"bh": "title", "en": "title", "d": 0.40172178962714566}, {"bh": "access-date", "en": "archive-date", "d": 0.4213962496304442}, {"bh": "booktitle", "en": "book-title", "d": 0.43459112081776474}, {"bh": "bibcode", "en": "bibcode", "d": 0.44095604041705694}], "Template:Full citation needed": [{"bh": "date", "en": "date", "d": 0.25855963384196023}], "Template:Infobox dam": [{"bh": "location", "en": "location", "d": 0.060850258779650335}, {"bh": "location_map", "en": "location_map", "d": 0.12585010776461147}, {"bh": "location_map_caption", "en": "location_map_caption", "d": 0.14915706776584803}, {"bh": "location_map_size", "en": "location_map_size", "d": 0.19051926494360272}, {"bh": "name", "en": "name", "d": 0.21803344649687106}, {"bh": "image", "en": "image", "d": 0.22816033235718702}, {"bh": "image_caption", "en": "image_caption", "d": 0.28013859500029614}, {"bh": "name_official", "en": "name_official", "d": 0.34772498478541236}, {"bh": "res_name", "en": "res_name", "d": 0.40438115769605554}, {"bh": "dam_width_base", "en": "image_size", "d": 0.4084054682713314}, {"bh": "coordinates", "en": "coordinates", "d": 0.42879033577169223}], "Template:Gutenberg author": [{"bh": "name", "en": "name", "d": 0.21803344649687106}, {"bh": "id", "en": "id", "d": 0.3498502040605166}], "Template:Infobox election": [], "Template:Infobox recurring event": [], "Template:Infobox scientist": [{"bh": "name", "en": "name", "d": 0.21803344649687106}, {"bh": "image", "en": "image", "d": 0.22816033235718702}, {"bh": "image_size", "en": "image_size", "d": 0.2591931448675111}, {"bh": "birth_date", "en": "birth_date", "d": 0.35864554242825275}, {"bh": "author_abbrev_bot", "en": "author_abbreviation_bot", "d": 0.36405821931027915}, {"bh": "birth_name", "en": "birth_name", "d": 0.3759942803669367}, {"bh": "thesis_url", "en": "thesis1_url", "d": 0.38132832657481597}, {"bh": "death_date", "en": "death_date", "d": 0.3870147463492204}, {"bh": "native_name", "en": "native_name", "d": 0.39954854057704536}, {"bh": "thesis_year", "en": "thesis2_year", "d": 0.43084084019037694}, {"bh": "footnotes", "en": "footnotes", "d": 0.4351583086810321}, {"bh": "author_abbrev_zoo", "en": "author_abbrev_bot", "d": 0.43630308606300505}], "Template:Cite thesis": [{"bh": "location", "en": "location", "d": 0.060850258779650335}, {"bh": "url", "en": "url", "d": 0.3011189705043299}, {"bh": "archivedate", "en": "archive-date", "d": 0.3250035585238501}, {"bh": "year", "en": "year", "d": 0.3251210168676537}, {"bh": "archiveurl", "en": "archive-url", "d": 0.33783504287025934}, {"bh": "id", "en": "id", "d": 0.3498502040605166}, {"bh": "title", "en": "title", "d": 0.40172178962714566}, {"bh": "accessdate", "en": "date", "d": 0.41725262971908406}], "Template:Infobox medical intervention": [{"bh": "name", "en": "name", "d": 0.21803344649687106}, {"bh": "image", "en": "image", "d": 0.22816033235718702}, {"bh": "other_codes", "en": "other_codes", "d": 0.3367912762532427}, {"bh": "icd9unlinked", "en": "icd9unlinked", "d": 0.36706903247844347}], "Template:Infobox nuclear weapons test": [{"bh": "name", "en": "name", "d": 0.21803344649687106}, {"bh": "country", "en": "country", "d": 0.31025609414271993}, {"bh": "picture_description", "en": "picture_description", "d": 0.36495043032700014}, {"bh": "picture", "en": "image", "d": 0.43490579725046086}], "Template:Chart top": [], "Template:Google books": [{"bh": "page", "en": "page", "d": 0.30010879197599183}, {"bh": "id", "en": "id", "d": 0.3498502040605166}, {"bh": "title", "en": "title", "d": 0.40172178962714566}], "Template:Cite peakbagger": [{"bh": "name", "en": "name", "d": 0.21803344649687106}, {"bh": "access-date", "en": "date", "d": 0.39396378305092017}, {"bh": "title", "en": "title", "d": 0.40172178962714566}], "Template:Infobox newspaper": [{"bh": "name", "en": "name", "d": 0.21803344649687106}, {"bh": "image", "en": "image", "d": 0.22816033235718702}, {"bh": "image_size", "en": "image_size", "d": 0.2591931448675111}, {"bh": "image_alt", "en": "image_alt", "d": 0.3435627961519965}, {"bh": "language", "en": "language", "d": 0.3662079943960146}, {"bh": "format", "en": "format", "d": 0.3769724366771072}, {"bh": "circulation_date", "en": "circulation_date", "d": 0.3966416492906373}, {"bh": "political", "en": "political", "d": 0.4123329714246867}], "Template:Infobox civilian attack": [{"bh": "location", "en": "location", "d": 0.060850258779650335}, {"bh": "date", "en": "date", "d": 0.25855963384196023}, {"bh": "title", "en": "title", "d": 0.40172178962714566}], "Template:Location map": [{"bh": "link", "en": "link", "d": 0.15649002414970536}, {"bh": "overlay_image", "en": "overlay_image", "d": 0.24440827673399756}, {"bh": "label_size", "en": "label_size", "d": 0.4033393459157938}, {"bh": "marksize", "en": "marksize", "d": 0.4351808437952549}], "Template:Infobox port": [{"bh": "location", "en": "location", "d": 0.060850258779650335}, {"bh": "name", "en": "name", "d": 0.21803344649687106}, {"bh": "image", "en": "image", "d": 0.22816033235718702}, {"bh": "country", "en": "country", "d": 0.31025609414271993}, {"bh": "imagesize", "en": "image_size", "d": 0.3301451936952574}, {"bh": "coordinates", "en": "coordinates", "d": 0.42879033577169223}], "Template:Infobox criminal": [{"bh": "name", "en": "name", "d": 0.21803344649687106}, {"bh": "birth_date", "en": "date", "d": 0.28512345377909987}, {"bh": "birth_name", "en": "image_name", "d": 0.31900606258969244}], "Template:Paraphyletic group": [{"bh": "name", "en": "name", "d": 0.21803344649687106}, {"bh": "image", "en": "image", "d": 0.22816033235718702}, {"bh": "image_upright", "en": "image_caption", "d": 0.27513035752550885}, {"bh": "image_caption", "en": "image_alt", "d": 0.36566461062483935}], "Template:Col-begin": [], "Template:Infobox bilateral relations": [], "Template:Structurae": [{"bh": "id", "en": "id", "d": 0.3498502040605166}, {"bh": "title", "en": "title", "d": 0.40172178962714566}], "Template:Infobox rail service": [{"bh": "name", "en": "name", "d": 0.21803344649687106}, {"bh": "image", "en": "image", "d": 0.22816033235718702}, {"bh": "map", "en": "map", "d": 0.29663798607129965}, {"bh": "map_state", "en": "map_state", "d": 0.3922585487601806}, {"bh": "end", "en": "end", "d": 0.43538968368728337}, {"bh": "trainnumber", "en": "train number", "d": 0.4354734131665854}, {"bh": "baggage", "en": "image_size", "d": 0.4414393822059254}], "Template:Skeptoid": [{"bh": "date", "en": "date", "d": 0.25855963384196023}, {"bh": "id", "en": "id", "d": 0.3498502040605166}, {"bh": "quote", "en": "quote", "d": 0.3583178396752551}, {"bh": "number", "en": "number", "d": 0.3859289249514911}, {"bh": "title", "en": "title", "d": 0.40172178962714566}], "Template:Infobox ancient site": [{"bh": "location", "en": "location", "d": 0.060850258779650335}, {"bh": "name", "en": "name", "d": 0.21803344649687106}, {"bh": "image", "en": "image", "d": 0.22816033235718702}, {"bh": "map_size", "en": "map_size", "d": 0.32857035188980477}, {"bh": "map_alt", "en": "map_caption", "d": 0.3288175263811245}, {"bh": "map_type", "en": "map_type", "d": 0.36125044153877994}, {"bh": "native_name", "en": "alternate_name", "d": 0.3638833290263488}, {"bh": "relief", "en": "map_label_position", "d": 0.4176405310312612}, {"bh": "alternate_name", "en": "designation2_free1name", "d": 0.42034329035825546}, {"bh": "epochs", "en": "delisted2_date", "d": 0.42799067400204327}, {"bh": "coordinates", "en": "coordinates", "d": 0.42879033577169223}], "Template:Infobox hospital": [], "Template:Hlist": [{"bh": "item_style", "en": "item_style", "d": 0.3995136610475386}, {"bh": "style", "en": "style", "d": 0.407025967647866}], "Template:Infobox zoo": [{"bh": "location", "en": "location", "d": 0.060850258779650335}, {"bh": "image", "en": "image", "d": 0.22816033235718702}, {"bh": "image_caption", "en": "image_caption", "d": 0.28013859500029614}, {"bh": "logo_caption", "en": "logo_caption", "d": 0.36272040640654934}, {"bh": "date_opened", "en": "date_opened", "d": 0.3688166571514303}, {"bh": "date_closed", "en": "date_closed", "d": 0.3794331589799682}, {"bh": "num_species", "en": "num_species", "d": 0.3869519752208438}, {"bh": "coordinates", "en": "coordinates", "d": 0.42879033577169223}], "Template:Infobox islands": [], "Template:Infobox planet": [{"bh": "name", "en": "name", "d": 0.21803344649687106}, {"bh": "image", "en": "image", "d": 0.22816033235718702}], "Template:Infobox dance": [{"bh": "name", "en": "name", "d": 0.21803344649687106}, {"bh": "image", "en": "image", "d": 0.22816033235718702}, {"bh": "year", "en": "year", "d": 0.3251210168676537}, {"bh": "imagesize", "en": "image_size", "d": 0.3301451936952574}, {"bh": "title", "en": "title", "d": 0.40172178962714566}], "Template:Infobox ship class overview": [{"bh": "name", "en": "name", "d": 0.21803344649687106}], "Template:Infobox automobile": [{"bh": "name", "en": "name", "d": 0.21803344649687106}, {"bh": "image", "en": "image", "d": 0.22816033235718702}], "Template:External media": [{"bh": "image8", "en": "image5", "d": 0.35067147249419994}, {"bh": "image10", "en": "image3", "d": 0.36235087325053605}, {"bh": "image11", "en": "image7", "d": 0.37758088051056293}, {"bh": "image1", "en": "image6", "d": 0.3824661966321219}, {"bh": "image7", "en": "image4", "d": 0.39382204441795543}, {"bh": "image4", "en": "image1", "d": 0.3957722314879637}, {"bh": "image9", "en": "caption", "d": 0.4004692760495703}, {"bh": "title", "en": "title", "d": 0.40172178962714566}, {"bh": "image6", "en": "image2", "d": 0.4030513558141474}], "Template:Infobox saint": [{"bh": "name", "en": "name", "d": 0.21803344649687106}, {"bh": "image", "en": "image", "d": 0.22816033235718702}, {"bh": "birth_date", "en": "birth_date", "d": 0.35864554242825275}, {"bh": "beatified_date", "en": "suppressed_date", "d": 0.3607847270667023}, {"bh": "death_date", "en": "death_date", "d": 0.3870147463492204}, {"bh": "canonized_date", "en": "canonized_date", "d": 0.4020839207601925}, {"bh": "titles", "en": "titles", "d": 0.44043271690858976}], "Template:Gallery": [{"bh": "title", "en": "title", "d": 0.40172178962714566}], "Template:Infobox cricket ground": [], "Template:Election box gain with party link": [], "Template:Tennis record": [], "Template:Main": [], "Template:Infobox sports team": [{"bh": "image", "en": "image", "d": 0.22816033235718702}, {"bh": "clubname", "en": "name", "d": 0.349588981270623}, {"bh": "fullname", "en": "full_name", "d": 0.40147177264982425}, {"bh": "upright", "en": "logo_size", "d": 0.41964544491835687}], "Template:Infobox architect": [{"bh": "name", "en": "name", "d": 0.21803344649687106}, {"bh": "image", "en": "image", "d": 0.22816033235718702}, {"bh": "birth_date", "en": "birth_date", "d": 0.35864554242825275}], "Template:Infobox gymnast": [], "Template:Infobox airport": [{"bh": "location", "en": "location", "d": 0.060850258779650335}, {"bh": "name", "en": "name", "d": 0.21803344649687106}, {"bh": "image", "en": "image", "d": 0.22816033235718702}, {"bh": "image-width", "en": "image_map_caption", "d": 0.29981244636870685}, {"bh": "pushpin_map", "en": "image_map", "d": 0.32102379967654127}, {"bh": "coordinates", "en": "coordinates", "d": 0.42879033577169223}, {"bh": "stat-year", "en": "stat-year", "d": 0.42993632757322353}, {"bh": "footnotes", "en": "footnotes", "d": 0.4351583086810321}], "Template:Lang-rus": [{"bh": "r", "en": "r", "d": 0.20586200832795898}, {"bh": "links", "en": "link", "d": 0.29725032393936757}], "Template:Infobox language": [{"bh": "name", "en": "name", "d": 0.21803344649687106}, {"bh": "image", "en": "image", "d": 0.22816033235718702}, {"bh": "date", "en": "date", "d": 0.25855963384196023}, {"bh": "map", "en": "map", "d": 0.29663798607129965}, {"bh": "notice", "en": "notice", "d": 0.3936024431071212}, {"bh": "states", "en": "states", "d": 0.41726384269785854}], "Template:Infobox character": [{"bh": "name", "en": "name", "d": 0.21803344649687106}, {"bh": "image", "en": "image", "d": 0.22816033235718702}, {"bh": "title", "en": "title", "d": 0.40172178962714566}], "Template:Twitter": [{"bh": "name", "en": "name", "d": 0.21803344649687106}, {"bh": "id", "en": "id", "d": 0.3498502040605166}], "Template:Infobox public transit": [], "Template:Cleanup": [{"bh": "date", "en": "date", "d": 0.25855963384196023}], "Template:Infobox deity": [{"bh": "name", "en": "name", "d": 0.21803344649687106}, {"bh": "image", "en": "image", "d": 0.22816033235718702}, {"bh": "sanskrit_transliteration", "en": "script_name", "d": 0.44553348727912}], "Template:Infobox bridge": [{"bh": "map_image", "en": "map_image", "d": 0.20003540186058466}, {"bh": "image", "en": "image", "d": 0.22816033235718702}, {"bh": "image_size", "en": "image_size", "d": 0.2591931448675111}, {"bh": "other_name", "en": "other_name", "d": 0.26042190828265943}, {"bh": "map_text", "en": "map_text", "d": 0.26361441168354227}, {"bh": "map_width", "en": "map_width", "d": 0.3033451446684897}, {"bh": "map_cue", "en": "map_caption", "d": 0.3080628632440714}, {"bh": "native_name", "en": "name", "d": 0.3170994222494702}, {"bh": "official_name", "en": "official_name", "d": 0.34772498478541236}, {"bh": "id", "en": "id", "d": 0.3498502040605166}, {"bh": "bridge_name", "en": "bridge_name", "d": 0.3986404080413336}, {"bh": "caption", "en": "location", "d": 0.40228095343102854}, {"bh": "width", "en": "mapframe_width", "d": 0.42249145342980254}, {"bh": "coordinates", "en": "coordinates", "d": 0.42879033577169223}], "Template:Harvp": [], "Template:Infobox occupation": [{"bh": "name", "en": "name", "d": 0.21803344649687106}, {"bh": "image", "en": "image", "d": 0.22816033235718702}], "Template:Wikisource-inline": [{"bh": "list", "en": "list", "d": 0.2106935456009802}], "Template:Bar box": [{"bh": "title", "en": "title", "d": 0.40172178962714566}, {"bh": "titlebar", "en": "titlebar", "d": 0.41454893111099433}], "Template:Cquote": [{"bh": "source", "en": "source", "d": 0.3030344350699311}, {"bh": "text", "en": "text", "d": 0.3534042633471749}], "Template:Blockquote": [{"bh": "source", "en": "source", "d": 0.3030344350699311}, {"bh": "text", "en": "text", "d": 0.3534042633471749}, {"bh": "quote", "en": "quote", "d": 0.3583178396752551}, {"bh": "title", "en": "title", "d": 0.40172178962714566}], "Template:Cite simbad": [{"bh": "title", "en": "title", "d": 0.40172178962714566}], "Template:Infobox mountain pass": [{"bh": "location", "en": "location", "d": 0.060850258779650335}, {"bh": "name", "en": "name", "d": 0.21803344649687106}, {"bh": "other_name", "en": "other_name", "d": 0.26042190828265943}, {"bh": "map_caption", "en": "map_caption", "d": 0.28735827570663164}, {"bh": "map", "en": "map", "d": 0.29663798607129965}, {"bh": "map_size", "en": "map_size", "d": 0.32857035188980477}, {"bh": "coordinates_ref", "en": "coordinates_ref", "d": 0.368535157065775}, {"bh": "coordinates", "en": "coords", "d": 0.3758311032700169}, {"bh": "photo_caption", "en": "photo_caption", "d": 0.4092280365722979}, {"bh": "coords", "en": "coordinates", "d": 0.44392629251357896}, {"bh": "photo_alt", "en": "photo_size", "d": 0.44583344668403446}], "Template:Infobox anatomy": [{"bh": "name", "en": "name", "d": 0.21803344649687106}, {"bh": "image", "en": "image", "d": 0.22816033235718702}, {"bh": "mapcaption", "en": "location", "d": 0.2839057719579413}, {"bh": "image2", "en": "caption", "d": 0.4005881660448951}], "Template:Native name": [{"bh": "icon", "en": "icon", "d": 0.42132517941143255}], "Template:Sic": [], "Template:Pp-vandalism": [], "Template:Cite ngs": [{"bh": "id", "en": "id", "d": 0.3498502040605166}, {"bh": "accessdate", "en": "date", "d": 0.41725262971908406}], "Template:Infobox valley": [{"bh": "location", "en": "location", "d": 0.060850258779650335}, {"bh": "name", "en": "name", "d": 0.21803344649687106}, {"bh": "photo_caption", "en": "map_image", "d": 0.3386315130985632}, {"bh": "coordinates", "en": "coordinates_ref", "d": 0.3771288847293417}], "Template:Infobox mineral": [{"bh": "category", "en": "category", "d": 0.15120470121779528}, {"bh": "name", "en": "name", "d": 0.21803344649687106}, {"bh": "image", "en": "image", "d": 0.22816033235718702}, {"bh": "color", "en": "color", "d": 0.23157110951604165}, {"bh": "imagesize", "en": "struct image", "d": 0.310186074478366}, {"bh": "other", "en": "other", "d": 0.34007514645099013}, {"bh": "fracture", "en": "struct caption", "d": 0.4101460849105111}, {"bh": "references", "en": "references", "d": 0.4327922736453268}], "Template:Subscription required": [{"bh": "date", "en": "date", "d": 0.25855963384196023}], "Template:Infobox international football competition": [], "Template:Virusbox": [{"bh": "image", "en": "image", "d": 0.22816033235718702}, {"bh": "image_caption", "en": "image_caption", "d": 0.28013859500029614}, {"bh": "image2", "en": "image2_caption", "d": 0.2936187613447844}, {"bh": "image_alt", "en": "image_alt", "d": 0.3435627961519965}, {"bh": "synonyms", "en": "synonyms_ref", "d": 0.44643632199761396}], "Template:Infobox media franchise": [{"bh": "image", "en": "image", "d": 0.22816033235718702}, {"bh": "title", "en": "italic_title", "d": 0.3680851333469627}], "Template:Infobox professional wrestler": [], "Template:Infobox medical condition": [{"bh": "name", "en": "name", "d": 0.21803344649687106}, {"bh": "image", "en": "image", "d": 0.22816033235718702}, {"bh": "symptoms", "en": "image_thumbtime", "d": 0.4123314117516925}], "Template:Notelist": [], "Template:Cite gvp": [{"bh": "name", "en": "name", "d": 0.21803344649687106}, {"bh": "accessdate", "en": "date", "d": 0.41725262971908406}], "Template:Nowrap": [], "Template:Infobox official post": [{"bh": "image", "en": "image", "d": 0.22816033235718702}, {"bh": "native_name", "en": "native_name", "d": 0.39954854057704536}, {"bh": "flag", "en": "flag", "d": 0.4005077454596606}, {"bh": "style", "en": "style", "d": 0.407025967647866}, {"bh": "flagsize", "en": "flagsize", "d": 0.44889107624400926}], "Template:Infobox flag": [{"bh": "name", "en": "name", "d": 0.21803344649687106}, {"bh": "image", "en": "image", "d": 0.22816033235718702}, {"bh": "use", "en": "use", "d": 0.2873936662533443}, {"bh": "image2", "en": "image_size", "d": 0.3548531374115397}], "Template:Infobox ecoregion": [], "Template:Infobox spaceflight": [{"bh": "name", "en": "name", "d": 0.21803344649687106}, {"bh": "image", "en": "image", "d": 0.22816033235718702}, {"bh": "image_size", "en": "image_size", "d": 0.2591931448675111}, {"bh": "image_caption", "en": "image_caption", "d": 0.28013859500029614}, {"bh": "launch_date", "en": "start_date", "d": 0.3810635399937359}, {"bh": "cospar_id", "en": "cospar_id", "d": 0.40191213929913017}], "Template:Time interval": [], "Template:Infobox examination": [{"bh": "language", "en": "language", "d": 0.3662079943960146}, {"bh": "year_started", "en": "year_terminated", "d": 0.40854872645432605}, {"bh": "test_admin", "en": "test_admin", "d": 0.4292980790407992}], "Template:Subspeciesbox": [{"bh": "name", "en": "name", "d": 0.21803344649687106}, {"bh": "image", "en": "image", "d": 0.22816033235718702}, {"bh": "species_link", "en": "species_link", "d": 0.25196155046554325}, {"bh": "image_upright", "en": "image_caption", "d": 0.27513035752550885}, {"bh": "image_caption", "en": "image2_caption", "d": 0.32561301887845184}, {"bh": "genus", "en": "species", "d": 0.41650157970903623}, {"bh": "synonyms", "en": "synonyms_ref", "d": 0.44643632199761396}], "Template:Lang": [{"bh": "link", "en": "link", "d": 0.15649002414970536}, {"bh": "links", "en": "links", "d": 0.3209053616927299}, {"bh": "italic", "en": "italic", "d": 0.44311040035330107}], "Template:Infobox instrument": [{"bh": "name", "en": "name", "d": 0.21803344649687106}, {"bh": "image", "en": "image", "d": 0.22816033235718702}, {"bh": "articles", "en": "articles", "d": 0.3875670958189691}], "Template:Infobox food": [{"bh": "name", "en": "name", "d": 0.21803344649687106}, {"bh": "image", "en": "image", "d": 0.22816033235718702}, {"bh": "country", "en": "country", "d": 0.31025609414271993}, {"bh": "other", "en": "other", "d": 0.34007514645099013}, {"bh": "alternate_name", "en": "alternate_name", "d": 0.3928591860169406}], "Template:Infobox waterfall": [{"bh": "location", "en": "location", "d": 0.060850258779650335}, {"bh": "name", "en": "name", "d": 0.21803344649687106}, {"bh": "map_caption", "en": "map_caption", "d": 0.28735827570663164}, {"bh": "map", "en": "map", "d": 0.29663798607129965}, {"bh": "map_width", "en": "map_width", "d": 0.3033451446684897}, {"bh": "photo_caption", "en": "map_image", "d": 0.3386315130985632}, {"bh": "photo_width", "en": "image_width", "d": 0.3413786494426867}, {"bh": "alt_name", "en": "alt_name", "d": 0.35860196861906335}, {"bh": "coordinates", "en": "coords_ref", "d": 0.37542267453030076}, {"bh": "average_width", "en": "map_size", "d": 0.39278953088994006}, {"bh": "coords", "en": "coords", "d": 0.40221660434215323}, {"bh": "average_flow", "en": "image_size", "d": 0.4219745124594375}, {"bh": "photo", "en": "image", "d": 0.44308181492541887}], "Template:Update after": [], "Template:Multiple releases": [{"bh": "date1", "en": "date4", "d": 0.42126047414474765}], "Template:Infobox pageant titleholder": [{"bh": "name", "en": "name", "d": 0.21803344649687106}, {"bh": "image", "en": "image", "d": 0.22816033235718702}, {"bh": "image_size", "en": "image_size", "d": 0.2591931448675111}, {"bh": "birth_date", "en": "birth_date", "d": 0.35864554242825275}, {"bh": "eye_color", "en": "eye_color", "d": 0.370834809156094}, {"bh": "birth_name", "en": "birth_name", "d": 0.3759942803669367}, {"bh": "death_date", "en": "death_date", "d": 0.3870147463492204}, {"bh": "title", "en": "title", "d": 0.40172178962714566}, {"bh": "hair_color", "en": "skin_color", "d": 0.4021103254248136}], "Template:Navbox": [{"bh": "name", "en": "name", "d": 0.21803344649687106}, {"bh": "image", "en": "image", "d": 0.22816033235718702}, {"bh": "list1", "en": "list4", "d": 0.3591369852353258}, {"bh": "list2", "en": "list6", "d": 0.36278296836898094}, {"bh": "title", "en": "title", "d": 0.40172178962714566}], "Template:Infobox economist": [{"bh": "name", "en": "name", "d": 0.21803344649687106}, {"bh": "image", "en": "image", "d": 0.22816033235718702}, {"bh": "birth_date", "en": "birth_date", "d": 0.35864554242825275}, {"bh": "death_date", "en": "death_date", "d": 0.3870147463492204}], "Template:Hidden begin": [{"bh": "title", "en": "title", "d": 0.40172178962714566}, {"bh": "titlestyle", "en": "contentstyle", "d": 0.4221497834274919}, {"bh": "toggle", "en": "toggle", "d": 0.44039738533107853}], "Template:Cite gnis": [{"bh": "name", "en": "name", "d": 0.21803344649687106}, {"bh": "id", "en": "id", "d": 0.3498502040605166}, {"bh": "entrydate", "en": "date", "d": 0.39738919372178527}], "Template:Infobox law enforcement agency": [], "Template:Infobox model": [{"bh": "name", "en": "name", "d": 0.21803344649687106}, {"bh": "image", "en": "image", "d": 0.22816033235718702}, {"bh": "imagesize", "en": "image_size", "d": 0.3301451936952574}, {"bh": "eyecolor", "en": "eye_color", "d": 0.3582473181557756}, {"bh": "birth_date", "en": "birth_date", "d": 0.35864554242825275}, {"bh": "birth_name", "en": "birth_name", "d": 0.3759942803669367}, {"bh": "death_date", "en": "death_date", "d": 0.3870147463492204}, {"bh": "haircolor", "en": "hair_color", "d": 0.38708184805966817}, {"bh": "haircolour", "en": "hair_colour", "d": 0.4441206170164077}], "Template:Infobox country": [{"bh": "image_map2", "en": "image_map", "d": 0.19488672170045052}, {"bh": "image_map", "en": "image_map_caption", "d": 0.1978253111601923}, {"bh": "image_flag", "en": "image_flag", "d": 0.25232805474573894}, {"bh": "map_caption", "en": "map_caption", "d": 0.28735827570663164}, {"bh": "currency_code", "en": "currency_code", "d": 0.28925507779569115}, {"bh": "image_coat", "en": "image_map2_caption", "d": 0.2946786333701559}, {"bh": "footnote_a", "en": "footnote_a", "d": 0.32979603233314314}, {"bh": "alt_map", "en": "image_map_alt", "d": 0.33183124298773714}, {"bh": "date_format", "en": "date_event5", "d": 0.34651544906733867}, {"bh": "languages2", "en": "languages", "d": 0.3496857512222338}, {"bh": "hdi_year", "en": "population_estimate_year", "d": 0.3554521986692616}, {"bh": "conventional_long_name", "en": "conventional_long_name", "d": 0.3559046592818218}, {"bh": "common_name", "en": "common_name", "d": 0.3676243479635548}, {"bh": "established_date6", "en": "date_event2", "d": 0.3701547825827337}, {"bh": "established_date5", "en": "date_event4", "d": 0.37431560898612315}, {"bh": "official_languages", "en": "official_languages", "d": 0.3808440818148138}, {"bh": "gini_year", "en": "hdi_year", "d": 0.38653185729327577}, {"bh": "gdp_ppp_year", "en": "gdp_nominal_year", "d": 0.3941191453378885}, {"bh": "native_name", "en": "native_name", "d": 0.39954854057704536}, {"bh": "established_date1", "en": "date_post", "d": 0.406975443964937}, {"bh": "established_date4", "en": "date_event1", "d": 0.40963776636896077}, {"bh": "established_date3", "en": "date_start", "d": 0.4168142030089421}, {"bh": "established_date7", "en": "date_event3", "d": 0.4180598805602592}, {"bh": "population_density_sq_mi", "en": "population_density_sq_mi", "d": 0.4233179905165225}, {"bh": "established_date2", "en": "date_end", "d": 0.424293965589543}, {"bh": "coordinates", "en": "coordinates", "d": 0.42879033577169223}, {"bh": "population_estimate_year", "en": "population_census_year", "d": 0.42964382858432637}, {"bh": "languages_type", "en": "languages_type", "d": 0.43258184286063683}, {"bh": "symbol_type", "en": "symbol_type", "d": 0.4340695229369186}, {"bh": "population_estimate_rank", "en": "population_estimate_rank", "d": 0.4364611138015214}, {"bh": "leader_title3", "en": "title_representative", "d": 0.43749239879329715}, {"bh": "currency", "en": "currency", "d": 0.44170231421174877}, {"bh": "calling_code", "en": "calling_code", "d": 0.44179253785545036}, {"bh": "population_density_rank", "en": "population_density_rank", "d": 0.4470683323193363}, {"bh": "map_width", "en": "image_map2", "d": 0.4489677016228487}], "Template:Map caption": [{"bh": "location_color", "en": "location_color", "d": 0.1443483098681244}, {"bh": "country", "en": "country", "d": 0.31025609414271993}, {"bh": "region_color", "en": "region_color", "d": 0.33414726815965246}, {"bh": "subregion_color", "en": "subregion_color", "d": 0.36431683986239394}, {"bh": "countryprefix", "en": "countryprefix", "d": 0.3894677301933517}], "Template:Sidebar": [{"bh": "title", "en": "title", "d": 0.40172178962714566}], "Template:Infobox broadcasting network": [{"bh": "country", "en": "country", "d": 0.31025609414271993}, {"bh": "network_name", "en": "name", "d": 0.3826953662671868}, {"bh": "launch_date", "en": "launch_date", "d": 0.4001922708880141}], "Template:Specify": [{"bh": "date", "en": "date", "d": 0.25855963384196023}], "Template:Infobox technology standard": [{"bh": "image", "en": "image", "d": 0.22816033235718702}, {"bh": "version_date", "en": "preview_date", "d": 0.3452434167374374}, {"bh": "title", "en": "title", "d": 0.40172178962714566}], "Template:Infobox character encoding": [{"bh": "name", "en": "name", "d": 0.21803344649687106}, {"bh": "image", "en": "image", "d": 0.22816033235718702}, {"bh": "encodes", "en": "encodings", "d": 0.41441634826861606}], "Template:End date and age": [], "Template:Infobox religious text": [{"bh": "image", "en": "image", "d": 0.22816033235718702}, {"bh": "language", "en": "language", "d": 0.3662079943960146}], "Template:Su": [], "Template:Infobox programming language": [{"bh": "latest preview date", "en": "latest preview date", "d": 0.3392679738537009}, {"bh": "file ext", "en": "file format", "d": 0.3689667526680994}, {"bh": "logo size", "en": "logo size", "d": 0.382559244531926}, {"bh": "latest release date", "en": "latest_test_date", "d": 0.4035342402956701}, {"bh": "latest preview version", "en": "latest preview version", "d": 0.4074527431984969}, {"bh": "wikibooks", "en": "wikibooks", "d": 0.43253132034263675}, {"bh": "logo", "en": "logo caption", "d": 0.4482412897463559}], "Template:Infobox executive government": [{"bh": "image", "en": "image", "d": 0.22816033235718702}, {"bh": "date", "en": "date", "d": 0.25855963384196023}, {"bh": "url", "en": "url", "d": 0.3011189705043299}, {"bh": "government_name", "en": "government_name", "d": 0.4025943808762329}], "Template:Europe topic": [{"bh": "template", "en": "template", "d": 0.16178577599982302}, {"bh": "title", "en": "title", "d": 0.40172178962714566}], "Template:Climate chart": [{"bh": "source", "en": "source", "d": 0.3030344350699311}], "Template:Infobox engineering career": [{"bh": "practice_name", "en": "practice_name", "d": 0.41724438983711243}], "Template:Infobox tunnel": [], "Template:Unbulleted list": [{"bh": "item1_style", "en": "item_style", "d": 0.3909284906995333}, {"bh": "style", "en": "style", "d": 0.407025967647866}], "Template:Longitem": [{"bh": "style", "en": "style", "d": 0.407025967647866}], "Template:Infobox electronic component": [{"bh": "photo", "en": "image_size", "d": 0.43811237810794945}], "Template:Infobox designation list": [{"bh": "designation1_date", "en": "designation2_date", "d": 0.2699022742079692}, {"bh": "designation1_number", "en": "designation2_number", "d": 0.29826688823782743}, {"bh": "designation1_free1name", "en": "designation2_free1name", "d": 0.34820682429196004}, {"bh": "designation1_free2name", "en": "designation1_free1name", "d": 0.36191037035737306}, {"bh": "designation1_free1value", "en": "designation2_free2value", "d": 0.3663916203756903}, {"bh": "designation1_free2value", "en": "designation2_free3value", "d": 0.37905298896212014}, {"bh": "designation1_type", "en": "designation2_type", "d": 0.3827077719347364}, {"bh": "designation1_offname", "en": "designation1_number", "d": 0.39364370733677}, {"bh": "designation1_criteria", "en": "designation2_criteria", "d": 0.3955530373493831}], "Template:Infobox poem": [{"bh": "name", "en": "name", "d": 0.21803344649687106}, {"bh": "language", "en": "language", "d": 0.3662079943960146}, {"bh": "original_title_lang", "en": "original_title_lang", "d": 0.38563981352114296}, {"bh": "original_title", "en": "original_title", "d": 0.4401678890775268}], "Template:Infobox anthem": [{"bh": "image", "en": "image", "d": 0.22816033235718702}, {"bh": "image_size", "en": "image_size", "d": 0.2591931448675111}, {"bh": "country", "en": "country", "d": 0.31025609414271993}, {"bh": "lyrics_date", "en": "music_date", "d": 0.3853951952633259}, {"bh": "title", "en": "title", "d": 0.40172178962714566}, {"bh": "music_date", "en": "lyrics_date", "d": 0.4239207491805318}], "Template:Infobox cinema market": [{"bh": "name", "en": "name", "d": 0.21803344649687106}, {"bh": "image", "en": "image", "d": 0.22816033235718702}, {"bh": "image_size", "en": "image_size", "d": 0.2591931448675111}, {"bh": "box_office_year", "en": "box_office_year", "d": 0.37199489393924656}, {"bh": "box_office_total", "en": "box_office_ref", "d": 0.3775652816849925}], "Template:Tree chart": [], "Template:Cite act": [{"bh": "date", "en": "date", "d": 0.25855963384196023}, {"bh": "url", "en": "url", "d": 0.3011189705043299}, {"bh": "article", "en": "article", "d": 0.3592828277867057}, {"bh": "number", "en": "number", "d": 0.3859289249514911}, {"bh": "title", "en": "title", "d": 0.40172178962714566}], "Template:Infobox referendum": [{"bh": "location", "en": "location", "d": 0.060850258779650335}, {"bh": "name", "en": "name", "d": 0.21803344649687106}, {"bh": "date", "en": "date", "d": 0.25855963384196023}, {"bh": "no_text", "en": "no_text", "d": 0.27079877718421475}, {"bh": "map", "en": "map", "d": 0.29663798607129965}, {"bh": "no", "en": "no", "d": 0.2971369470004025}, {"bh": "title", "en": "title", "d": 0.40172178962714566}, {"bh": "yes_text", "en": "yes_text", "d": 0.42749899932832014}], "Template:Legend inline": [], "Template:Solar mass": [{"bh": "link", "en": "link", "d": 0.15649002414970536}], "Template:Image label begin": [{"bh": "link", "en": "link", "d": 0.15649002414970536}, {"bh": "image", "en": "image", "d": 0.22816033235718702}], "Template:Image label": [{"bh": "text", "en": "text", "d": 0.3534042633471749}, {"bh": "x", "en": "x", "d": 0.4455230693750525}], "Template:Infobox unit": [{"bh": "name", "en": "name", "d": 0.21803344649687106}, {"bh": "image", "en": "image", "d": 0.22816033235718702}], "Template:Switcher": [], "Template:S-new": [], "Template:Bulleted list": [{"bh": "item_style", "en": "item_style", "d": 0.3995136610475386}, {"bh": "style", "en": "style", "d": 0.407025967647866}], "Template:Infobox economy": [], "Template:Infobox national military": [], "Template:Infobox drug": [], "Template:Infobox astronaut": [{"bh": "name", "en": "name", "d": 0.21803344649687106}, {"bh": "image", "en": "image", "d": 0.22816033235718702}, {"bh": "birth_date", "en": "birth_date", "d": 0.35864554242825275}], "Template:Infobox national football team": [], "Template:Asia topic": [{"bh": "title", "en": "title", "d": 0.40172178962714566}], "Template:Statoids": [{"bh": "id", "en": "id", "d": 0.3498502040605166}, {"bh": "title", "en": "title", "d": 0.40172178962714566}], "Template:Font": [], "Template:According to whom": [{"bh": "date", "en": "date", "d": 0.25855963384196023}], "Template:Cricketarchive": [{"bh": "id", "en": "id", "d": 0.3498502040605166}], "Template:Age in years and days": [], "Template:S-inc": [], "Template:Infobox nebula": [{"bh": "name", "en": "name", "d": 0.21803344649687106}, {"bh": "image", "en": "image", "d": 0.22816033235718702}, {"bh": "image_size", "en": "image_size", "d": 0.2591931448675111}], "Template:Infobox embryology": [{"bh": "name", "en": "name", "d": 0.21803344649687106}, {"bh": "image", "en": "image", "d": 0.22816033235718702}, {"bh": "image2", "en": "caption", "d": 0.4005881660448951}], "Template:Infobox militant organization": [], "Template:\u20ac": [{"bh": "link", "en": "link", "d": 0.15649002414970536}], "Template:Flagcountry": [], "Template:Track listing": [{"bh": "title3", "en": "title7", "d": 0.38574665674977127}, {"bh": "title4", "en": "title20", "d": 0.39293889122806647}, {"bh": "title6", "en": "title24", "d": 0.394849691024565}, {"bh": "title2", "en": "title27", "d": 0.39609336400875317}, {"bh": "title1", "en": "title9", "d": 0.4021221253655919}, {"bh": "title7", "en": "title26", "d": 0.4140602212789358}, {"bh": "title5", "en": "title6", "d": 0.4149518111259771}, {"bh": "extra_column", "en": "extra_width", "d": 0.4380702684159573}], "Template:Infobox civil conflict": [], "Template:Start and end dates": [], "Template:Infobox film or theatre festival": [{"bh": "location", "en": "location", "d": 0.060850258779650335}, {"bh": "name", "en": "name", "d": 0.21803344649687106}, {"bh": "image", "en": "image", "d": 0.22816033235718702}, {"bh": "image_size", "en": "image_size", "d": 0.2591931448675111}, {"bh": "language", "en": "language", "d": 0.3662079943960146}, {"bh": "number", "en": "number", "d": 0.3859289249514911}], "Template:Infobox algorithm": [{"bh": "image", "en": "image", "d": 0.22816033235718702}, {"bh": "data", "en": "data", "d": 0.2526165405689711}, {"bh": "best-time", "en": "time", "d": 0.3959352229225779}], "Template:Infobox artifact": [{"bh": "location", "en": "location", "d": 0.060850258779650335}, {"bh": "name", "en": "name", "d": 0.21803344649687106}, {"bh": "image", "en": "image", "d": 0.22816033235718702}, {"bh": "image_caption", "en": "image_caption", "d": 0.28013859500029614}, {"bh": "map", "en": "map", "d": 0.29663798607129965}, {"bh": "id", "en": "id", "d": 0.3498502040605166}, {"bh": "size", "en": "image_size", "d": 0.4033520265352766}], "Template:Image label small": [{"bh": "text", "en": "text", "d": 0.3534042633471749}, {"bh": "x", "en": "x", "d": 0.4455230693750525}], "Template:Infobox toy": [{"bh": "name", "en": "name", "d": 0.21803344649687106}, {"bh": "image", "en": "image", "d": 0.22816033235718702}, {"bh": "country", "en": "country", "d": 0.31025609414271993}, {"bh": "to", "en": "to", "d": 0.3371125762670881}, {"bh": "from", "en": "from", "d": 0.423432523828458}], "Template:Incubator": [{"bh": "code", "en": "code", "d": 0.37987622405765586}], "Template:Infobox physical quantity": [{"bh": "name", "en": "name", "d": 0.21803344649687106}, {"bh": "image", "en": "image", "d": 0.22816033235718702}], "Template:Africa topic": [{"bh": "title", "en": "title", "d": 0.40172178962714566}], "Template:Contains special characters": [], "Template:Image array": [{"bh": "image8", "en": "image5", "d": 0.35067147249419994}, {"bh": "image1", "en": "image9", "d": 0.36081489984131365}, {"bh": "image4", "en": "image3", "d": 0.363421395764817}, {"bh": "image3", "en": "image7", "d": 0.3797158323261093}, {"bh": "image7", "en": "image6", "d": 0.38368886949929715}, {"bh": "image6", "en": "image8", "d": 0.3895027568739843}, {"bh": "image5", "en": "image4", "d": 0.3938799379157807}, {"bh": "image2", "en": "caption12", "d": 0.39527083715243316}], "Template:Infobox treaty": [{"bh": "name", "en": "name", "d": 0.21803344649687106}, {"bh": "image", "en": "image", "d": 0.22816033235718702}, {"bh": "image_width", "en": "image_width", "d": 0.2883721324880065}, {"bh": "date_expiration", "en": "date_expiration", "d": 0.3139783735192885}, {"bh": "date_effective", "en": "date_expiry", "d": 0.3483278086387479}, {"bh": "location_signed", "en": "location_signed", "d": 0.34961725361787854}, {"bh": "date_sealed", "en": "date_ratified", "d": 0.3573471041243046}, {"bh": "languages", "en": "languages", "d": 0.3582518186549172}, {"bh": "long_name", "en": "long_name", "d": 0.35843648556573515}, {"bh": "language", "en": "language", "d": 0.3662079943960146}, {"bh": "wikisource", "en": "wikisource2", "d": 0.4013124800655279}, {"bh": "date_drafted", "en": "date_sealed", "d": 0.40373039421753765}, {"bh": "date_signed", "en": "date_signed", "d": 0.4339053288673086}], "Template:Infobox mythical creature": [{"bh": "name", "en": "name", "d": 0.21803344649687106}, {"bh": "image", "en": "image", "d": 0.22816033235718702}, {"bh": "sub_grouping", "en": "sub_grouping", "d": 0.3795525890899625}], "Template:Percentage": [], "Template:Commons category-inline": [], "Template:Infobox top level domain": [], "Template:Infobox product": [{"bh": "image", "en": "image", "d": 0.22816033235718702}, {"bh": "image_size", "en": "image_size", "d": 0.2591931448675111}, {"bh": "title", "en": "title", "d": 0.40172178962714566}], "Template:Infobox geographical indication": [{"bh": "name", "en": "name", "d": 0.21803344649687106}, {"bh": "image", "en": "image", "d": 0.22816033235718702}, {"bh": "image_size", "en": "image_size", "d": 0.2591931448675111}, {"bh": "country", "en": "country", "d": 0.31025609414271993}, {"bh": "alternative names", "en": "alternative names", "d": 0.43785215486266826}], "Template:Infobox cricket tournament main": [{"bh": "name", "en": "name", "d": 0.21803344649687106}, {"bh": "image", "en": "image", "d": 0.22816033235718702}], "Template:Infobox oil refinery": [{"bh": "location_map", "en": "location_map", "d": 0.12585010776461147}, {"bh": "name", "en": "name", "d": 0.21803344649687106}, {"bh": "image", "en": "image", "d": 0.22816033235718702}, {"bh": "country", "en": "country", "d": 0.31025609414271993}, {"bh": "image alt", "en": "image alt", "d": 0.3435627961519965}, {"bh": "caption", "en": "location_map_width", "d": 0.37152980132807134}, {"bh": "coordinates", "en": "coordinates_ref", "d": 0.3771288847293417}, {"bh": "oil refining center", "en": "location_map_text", "d": 0.41314205121747927}], "Template:Infobox archaeological culture": [{"bh": "name", "en": "name", "d": 0.21803344649687106}, {"bh": "map", "en": "map", "d": 0.29663798607129965}], "Template:Harvcol": [], "Template:Infobox machine": [], "Template:Infobox residential college": [], "Template:Infobox hieroglyphs": [{"bh": "name", "en": "name", "d": 0.21803344649687106}, {"bh": "image1 description", "en": "image1 description", "d": 0.3228857495284576}, {"bh": "name transcription", "en": "name explanation", "d": 0.3291675404475092}, {"bh": "image1-width", "en": "image1-width", "d": 0.3768129307218063}, {"bh": "image1", "en": "image1", "d": 0.39564242320819587}], "Template:Geological range": [], "Template:Lang-tr": [{"bh": "italic", "en": "italic", "d": 0.44311040035330107}], "Template:Leftlegend": [], "Template:Infobox poultry breed": [{"bh": "name", "en": "name", "d": 0.21803344649687106}, {"bh": "image", "en": "image", "d": 0.22816033235718702}, {"bh": "image_size", "en": "image_size", "d": 0.2591931448675111}, {"bh": "use", "en": "use", "d": 0.2873936662533443}, {"bh": "country", "en": "country", "d": 0.31025609414271993}, {"bh": "note", "en": "note", "d": 0.34428536778158414}, {"bh": "eggcolor", "en": "eggcolour", "d": 0.42008634681623735}, {"bh": "skincolor", "en": "eggcolor", "d": 0.43370480476070383}], "Template:Infobox rock": [{"bh": "name", "en": "name", "d": 0.21803344649687106}, {"bh": "image", "en": "image", "d": 0.22816033235718702}, {"bh": "image_size", "en": "image_size", "d": 0.2591931448675111}, {"bh": "image_caption", "en": "image_caption", "d": 0.28013859500029614}, {"bh": "alternative_name", "en": "alternative_name", "d": 0.3245634754956638}], "Template:Infobox drug class": [{"bh": "name", "en": "name", "d": 0.21803344649687106}, {"bh": "image", "en": "image", "d": 0.22816033235718702}, {"bh": "use", "en": "use", "d": 0.2873936662533443}], "Template:Oceania topic": [{"bh": "title", "en": "title", "d": 0.40172178962714566}], "Template:Infobox laboratory equipment": [{"bh": "name", "en": "name", "d": 0.21803344649687106}, {"bh": "image", "en": "image", "d": 0.22816033235718702}, {"bh": "uses", "en": "uses", "d": 0.3980361081331877}], "Template:Double-dagger": [], "Template:Infobox project": [{"bh": "image", "en": "image", "d": 0.22816033235718702}, {"bh": "country", "en": "country", "d": 0.31025609414271993}, {"bh": "native_name", "en": "name", "d": 0.3170994222494702}, {"bh": "caption", "en": "location", "d": 0.40228095343102854}], "Template:Infobox space agency": [{"bh": "name", "en": "name", "d": 0.21803344649687106}, {"bh": "image", "en": "image", "d": 0.22816033235718702}, {"bh": "url", "en": "url", "d": 0.3011189705043299}, {"bh": "native_name", "en": "native_name", "d": 0.39954854057704536}], "Template:Infobox nutritional value": [{"bh": "name", "en": "name", "d": 0.21803344649687106}, {"bh": "image", "en": "image", "d": 0.22816033235718702}, {"bh": "source_usda", "en": "source", "d": 0.31442921995015627}], "Template:Term": [{"bh": "content", "en": "content", "d": 0.40575085898989305}], "Template:Legend0": [], "Template:Standard banknote table notice": [], "Template:Infobox central bank": [], "Template:Infobox tool": [{"bh": "name", "en": "name", "d": 0.21803344649687106}, {"bh": "image", "en": "image", "d": 0.22816033235718702}, {"bh": "image size", "en": "image size", "d": 0.2591931448675111}, {"bh": "other_name", "en": "other_name", "d": 0.26042190828265943}, {"bh": "used_with", "en": "used_with", "d": 0.37145443813040935}], "Template:Infobox month": [{"bh": "image", "en": "image", "d": 0.22816033235718702}, {"bh": "native_name", "en": "native_name", "d": 0.39954854057704536}], "Template:Infobox raga": [{"bh": "image_name", "en": "image_name", "d": 0.19319794457156225}, {"bh": "name", "en": "name", "d": 0.21803344649687106}, {"bh": "image_alt", "en": "image_alt", "d": 0.3435627961519965}]}